{"compSeason":{"label":"2002/03","competition":{"abbreviation":"EN_PR","description":"Premier League","level":"SEN","source":"","id":1,"altIds":{"opta":"8"}},"id":11},"live":false,"dynamicallyGenerated":true,"tables":[{"gameWeek":0,"entries":[{"team":{"name":"Manchester United","club":{"name":"Manchester United","shortName":"Man Utd","abbr":"MUN","id":12},"teamType":"FIRST","shortName":"Man Utd","id":12,"altIds":{"opta":"t1"}},"position":1,"startingPosition":1,"overall":{"played":35,"won":22,"drawn":8,"lost":5,"goalsFor":66,"goalsAgainst":32,"goalsDifference":34,"points":74},"home":{"played":18,"won":15,"drawn":2,"lost":1,"goalsFor":38,"goalsAgainst":11,"goalsDifference":27,"points":47,"position":1},"away":{"played":17,"won":7,"drawn":6,"lost":4,"goalsFor":28,"goalsAgainst":21,"goalsDifference":7,"points":27,"position":2},"annotations":[{"type":"Q","destination":"EU_CL"}],"form":[{"gameweek":{"id":427,"gameweek":31},"kickoff":{"completeness":3,"millis":1048336200000,"label":"Sat 22 Mar 2003, 12:30 GMT"},"provisionalKickoff":{"completeness":0},"teams":[{"team":{"name":"Manchester United","club":{"name":"Manchester United","shortName":"Man Utd","abbr":"MUN","id":12},"teamType":"FIRST","shortName":"Man Utd","id":12,"altIds":{"opta":"t1"}},"score":3},{"team":{"name":"Fulham","club":{"name":"Fulham","shortName":"Fulham","abbr":"FUL","id":34},"teamType":"FIRST","shortName":"Fulham","id":34,"altIds":{"opta":"t54"}},"score":0}],"replay":false,"ground":{"name":"Old Trafford","city":"Manchester","source":"OPTA","id":3},"neutralGround":false,"status":"C","phase":"F","outcome":"H","attendance":67706,"clock":{"secs":5400,"label":"90\u002700"},"id":4349,"altIds":{"opta":"g16043"}},{"gameweek":{"id":428,"gameweek":32},"kickoff":{"completeness":3,"millis":1049542200000,"label":"Sat 5 Apr 2003, 12:30 BST","gmtOffset":1.0},"provisionalKickoff":{"completeness":0},"teams":[{"team":{"name":"Manchester United","club":{"name":"Manchester United","shortName":"Man Utd","abbr":"MUN","id":12},"teamType":"FIRST","shortName":"Man Utd","id":12,"altIds":{"opta":"t1"}},"score":4},{"team":{"name":"Liverpool","club":{"name":"Liverpool","shortName":"Liverpool","abbr":"LIV","id":10},"teamType":"FIRST","shortName":"Liverpool","id":10,"altIds":{"opta":"t14"}},"score":0}],"replay":false,"ground":{"name":"Old Trafford","city":"Manchester","source":"OPTA","id":3},"neutralGround":false,"status":"C","phase":"F","outcome":"H","attendance":67639,"clock":{"secs":5400,"label":"90\u002700"},"id":4360,"altIds":{"opta":"g16776"}},{"gameweek":{"id":429,"gameweek":33},"kickoff":{"completeness":3,"millis":1050147000000,"label":"Sat 12 Apr 2003, 12:30 BST","gmtOffset":1.0},"provisionalKickoff":{"completeness":0},"teams":[{"team":{"name":"Newcastle United","club":{"name":"Newcastle United","shortName":"Newcastle","abbr":"NEW","id":23},"teamType":"FIRST","shortName":"Newcastle","id":23,"altIds":{"opta":"t4"}},"score":2},{"team":{"name":"Manchester United","club":{"name":"Manchester United","shortName":"Man Utd","abbr":"MUN","id":12},"teamType":"FIRST","shortName":"Man Utd","id":12,"altIds":{"opta":"t1"}},"score":6}],"replay":false,"ground":{"name":"St. James\u0027 Park","city":"Newcastle","source":"OPTA","id":21},"neutralGround":false,"status":"C","phase":"F","outcome":"A","attendance":52164,"clock":{"secs":5400,"label":"90\u002700"},"id":4373,"altIds":{"opta":"g17073"}},{"gameweek":{"id":429,"gameweek":33},"kickoff":{"completeness":3,"millis":1050519600000,"label":"Wed 16 Apr 2003, 20:00 BST","gmtOffset":1.0},"provisionalKickoff":{"completeness":0},"teams":[{"team":{"name":"Arsenal","club":{"name":"Arsenal","shortName":"Arsenal","abbr":"ARS","id":1},"teamType":"FIRST","shortName":"Arsenal","id":1,"altIds":{"opta":"t3"}},"score":2},{"team":{"name":"Manchester United","club":{"name":"Manchester United","shortName":"Man Utd","abbr":"MUN","id":12},"teamType":"FIRST","shortName":"Man Utd","id":12,"altIds":{"opta":"t1"}},"score":2}],"replay":false,"ground":{"name":"Highbury","city":"London","source":"OPTA","id":302},"neutralGround":false,"status":"C","phase":"F","outcome":"D","attendance":38164,"clock":{"secs":5400,"label":"90\u002700"},"id":4376,"altIds":{"opta":"g13744"}},{"gameweek":{"id":430,"gameweek":34},"kickoff":{"completeness":3,"millis":1050760800000,"label":"Sat 19 Apr 2003, 15:00 BST","gmtOffset":1.0},"provisionalKickoff":{"completeness":0},"teams":[{"team":{"name":"Manchester United","club":{"name":"Manchester United","shortName":"Man Utd","abbr":"MUN","id":12},"teamType":"FIRST","shortName":"Man Utd","id":12,"altIds":{"opta":"t1"}},"score":3},{"team":{"name":"Blackburn Rovers","club":{"name":"Blackburn Rovers","shortName":"Blackburn","abbr":"BLB","id":3},"teamType":"FIRST","shortName":"Blackburn","id":3,"altIds":{"opta":"t5"}},"score":1}],"replay":false,"ground":{"name":"Old Trafford","city":"Manchester","source":"OPTA","id":3},"neutralGround":false,"status":"C","phase":"F","outcome":"H","attendance":67626,"clock":{"secs":5400,"label":"90\u002700"},"id":4383,"altIds":{"opta":"g14536"}}],"ground":{"name":"Old Trafford","city":"Manchester","capacity":75811,"location":{"latitude":53.4626,"longitude":-2.29103},"source":"OPTA","id":3}},{"team":{"name":"Arsenal","club":{"name":"Arsenal","shortName":"Arsenal","abbr":"ARS","id":1},"teamType":"FIRST","shortName":"Arsenal","id":1,"altIds":{"opta":"t3"}},"position":2,"startingPosition":2,"overall":{"played":34,"won":21,"drawn":8,"lost":5,"goalsFor":71,"goalsAgainst":36,"goalsDifference":35,"points":71},"home":{"played":17,"won":14,"drawn":2,"lost":1,"goalsFor":39,"goalsAgainst":16,"goalsDifference":23,"points":44,"position":2},"away":{"played":17,"won":7,"drawn":6,"lost":4,"goalsFor":32,"goalsAgainst":20,"goalsDifference":12,"points":27,"position":1},"annotations":[{"type":"Q","destination":"EU_CL"}],"form":[{"gameweek":{"id":426,"gameweek":30},"kickoff":{"completeness":3,"millis":1047740400000,"label":"Sat 15 Mar 2003, 15:00 GMT"},"provisionalKickoff":{"completeness":0},"teams":[{"team":{"name":"Blackburn Rovers","club":{"name":"Blackburn Rovers","shortName":"Blackburn","abbr":"BLB","id":3},"teamType":"FIRST","shortName":"Blackburn","id":3,"altIds":{"opta":"t5"}},"score":2},{"team":{"name":"Arsenal","club":{"name":"Arsenal","shortName":"Arsenal","abbr":"ARS","id":1},"teamType":"FIRST","shortName":"Arsenal","id":1,"altIds":{"opta":"t3"}},"score":0}],"replay":false,"ground":{"name":"Ewood Park","city":"Blackburn","source":"OPTA","id":5},"neutralGround":false,"status":"C","phase":"F","outcome":"H","attendance":29840,"clock":{"secs":5400,"label":"90\u002700"},"id":4338,"altIds":{"opta":"g13741"}},{"gameweek":{"id":427,"gameweek":31},"kickoff":{"completeness":3,"millis":1048435500000,"label":"Sun 23 Mar 2003, 16:05 GMT"},"provisionalKickoff":{"completeness":0},"teams":[{"team":{"name":"Arsenal","club":{"name":"Arsenal","shortName":"Arsenal","abbr":"ARS","id":1},"teamType":"FIRST","shortName":"Arsenal","id":1,"altIds":{"opta":"t3"}},"score":2},{"team":{"name":"Everton","club":{"name":"Everton","shortName":"Everton","abbr":"EVE","id":7},"teamType":"FIRST","shortName":"Everton","id":7,"altIds":{"opta":"t11"}},"score":1}],"replay":false,"ground":{"name":"Highbury","city":"London","source":"OPTA","id":302},"neutralGround":false,"status":"C","phase":"F","outcome":"H","attendance":38042,"clock":{"secs":5400,"label":"90\u002700"},"id":4354,"altIds":{"opta":"g13742"}},{"gameweek":{"id":428,"gameweek":32},"kickoff":{"completeness":3,"millis":1049551200000,"label":"Sat 5 Apr 2003, 15:00 BST","gmtOffset":1.0},"provisionalKickoff":{"completeness":0},"teams":[{"team":{"name":"Aston Villa","club":{"name":"Aston Villa","shortName":"Aston Villa","abbr":"AVL","id":2},"teamType":"FIRST","shortName":"Aston Villa","id":2,"altIds":{"opta":"t7"}},"score":1},{"team":{"name":"Arsenal","club":{"name":"Arsenal","shortName":"Arsenal","abbr":"ARS","id":1},"teamType":"FIRST","shortName":"Arsenal","id":1,"altIds":{"opta":"t3"}},"score":1}],"replay":false,"ground":{"name":"Villa Park","city":"Birmingham","source":"OPTA","id":7},"neutralGround":false,"status":"C","phase":"F","outcome":"D","attendance":42602,"clock":{"secs":5400,"label":"90\u002700"},"id":4357,"altIds":{"opta":"g13743"}},{"gameweek":{"id":429,"gameweek":33},"kickoff":{"completeness":3,"millis":1050519600000,"label":"Wed 16 Apr 2003, 20:00 BST","gmtOffset":1.0},"provisionalKickoff":{"completeness":0},"teams":[{"team":{"name":"Arsenal","club":{"name":"Arsenal","shortName":"Arsenal","abbr":"ARS","id":1},"teamType":"FIRST","shortName":"Arsenal","id":1,"altIds":{"opta":"t3"}},"score":2},{"team":{"name":"Manchester United","club":{"name":"Manchester United","shortName":"Man Utd","abbr":"MUN","id":12},"teamType":"FIRST","shortName":"Man Utd","id":12,"altIds":{"opta":"t1"}},"score":2}],"replay":false,"ground":{"name":"Highbury","city":"London","source":"OPTA","id":302},"neutralGround":false,"status":"C","phase":"F","outcome":"D","attendance":38164,"clock":{"secs":5400,"label":"90\u002700"},"id":4376,"altIds":{"opta":"g13744"}},{"gameweek":{"id":430,"gameweek":34},"kickoff":{"completeness":3,"millis":1050760800000,"label":"Sat 19 Apr 2003, 15:00 BST","gmtOffset":1.0},"provisionalKickoff":{"completeness":0},"teams":[{"team":{"name":"Middlesbrough","club":{"name":"Middlesbrough","shortName":"Middlesbrough","abbr":"MID","id":13},"teamType":"FIRST","shortName":"Middlesbrough","id":13,"altIds":{"opta":"t25"}},"score":0},{"team":{"name":"Arsenal","club":{"name":"Arsenal","shortName":"Arsenal","abbr":"ARS","id":1},"teamType":"FIRST","shortName":"Arsenal","id":1,"altIds":{"opta":"t3"}},"score":2}],"replay":false,"ground":{"name":"Riverside Stadium","city":"Middlesbrough","source":"OPTA","id":61},"neutralGround":false,"status":"C","phase":"F","outcome":"A","attendance":34724,"clock":{"secs":5400,"label":"90\u002700"},"id":4384,"altIds":{"opta":"g13745"}}],"ground":{"name":"Highbury","city":"London","location":{"latitude":53.9182,"longitude":-3.02187},"source":"OPTA","id":302}},{"team":{"name":"Newcastle United","club":{"name":"Newcastle United","shortName":"Newcastle","abbr":"NEW","id":23},"teamType":"FIRST","shortName":"Newcastle","id":23,"altIds":{"opta":"t4"}},"position":3,"startingPosition":3,"overall":{"played":34,"won":19,"drawn":4,"lost":11,"goalsFor":58,"goalsAgainst":45,"goalsDifference":13,"points":61},"home":{"played":17,"won":14,"drawn":1,"lost":2,"goalsFor":34,"goalsAgainst":16,"goalsDifference":18,"points":43,"position":3},"away":{"played":17,"won":5,"drawn":3,"lost":9,"goalsFor":24,"goalsAgainst":29,"goalsDifference":-5,"points":18,"position":11},"annotations":[{"type":"Q","destination":"EU_CL"}],"form":[{"gameweek":{"id":426,"gameweek":30},"kickoff":{"completeness":3,"millis":1047740400000,"label":"Sat 15 Mar 2003, 15:00 GMT"},"provisionalKickoff":{"completeness":0},"teams":[{"team":{"name":"Charlton Athletic","club":{"name":"Charlton Athletic","shortName":"Charlton","abbr":"CHA","id":31},"teamType":"FIRST","shortName":"Charlton","id":31,"altIds":{"opta":"t33"}},"score":0},{"team":{"name":"Newcastle United","club":{"name":"Newcastle United","shortName":"Newcastle","abbr":"NEW","id":23},"teamType":"FIRST","shortName":"Newcastle","id":23,"altIds":{"opta":"t4"}},"score":2}],"replay":false,"ground":{"name":"The Valley","city":"London","source":"OPTA","id":63},"neutralGround":false,"status":"C","phase":"F","outcome":"A","attendance":26728,"clock":{"secs":5400,"label":"90\u002700"},"id":4339,"altIds":{"opta":"g14850"}},{"gameweek":{"id":427,"gameweek":31},"kickoff":{"completeness":3,"millis":1048345200000,"label":"Sat 22 Mar 2003, 15:00 GMT"},"provisionalKickoff":{"completeness":0},"teams":[{"team":{"name":"Newcastle United","club":{"name":"Newcastle United","shortName":"Newcastle","abbr":"NEW","id":23},"teamType":"FIRST","shortName":"Newcastle","id":23,"altIds":{"opta":"t4"}},"score":5},{"team":{"name":"Blackburn Rovers","club":{"name":"Blackburn Rovers","shortName":"Blackburn","abbr":"BLB","id":3},"teamType":"FIRST","shortName":"Blackburn","id":3,"altIds":{"opta":"t5"}},"score":1}],"replay":false,"ground":{"name":"St. James\u0027 Park","city":"Newcastle","source":"OPTA","id":21},"neutralGround":false,"status":"C","phase":"F","outcome":"H","attendance":52106,"clock":{"secs":5400,"label":"90\u002700"},"id":4351,"altIds":{"opta":"g14533"}},{"gameweek":{"id":428,"gameweek":32},"kickoff":{"completeness":3,"millis":1049641200000,"label":"Sun 6 Apr 2003, 16:00 BST","gmtOffset":1.0},"provisionalKickoff":{"completeness":0},"teams":[{"team":{"name":"Everton","club":{"name":"Everton","shortName":"Everton","abbr":"EVE","id":7},"teamType":"FIRST","shortName":"Everton","id":7,"altIds":{"opta":"t11"}},"score":2},{"team":{"name":"Newcastle United","club":{"name":"Newcastle United","shortName":"Newcastle","abbr":"NEW","id":23},"teamType":"FIRST","shortName":"Newcastle","id":23,"altIds":{"opta":"t4"}},"score":1}],"replay":false,"ground":{"name":"Goodison Park","city":"Liverpool","source":"OPTA","id":9},"neutralGround":false,"status":"C","phase":"F","outcome":"H","attendance":40031,"clock":{"secs":5400,"label":"90\u002700"},"id":4365,"altIds":{"opta":"g15998"}},{"gameweek":{"id":429,"gameweek":33},"kickoff":{"completeness":3,"millis":1050147000000,"label":"Sat 12 Apr 2003, 12:30 BST","gmtOffset":1.0},"provisionalKickoff":{"completeness":0},"teams":[{"team":{"name":"Newcastle United","club":{"name":"Newcastle United","shortName":"Newcastle","abbr":"NEW","id":23},"teamType":"FIRST","shortName":"Newcastle","id":23,"altIds":{"opta":"t4"}},"score":2},{"team":{"name":"Manchester United","club":{"name":"Manchester United","shortName":"Man Utd","abbr":"MUN","id":12},"teamType":"FIRST","shortName":"Man Utd","id":12,"altIds":{"opta":"t1"}},"score":6}],"replay":false,"ground":{"name":"St. James\u0027 Park","city":"Newcastle","source":"OPTA","id":21},"neutralGround":false,"status":"C","phase":"F","outcome":"A","attendance":52164,"clock":{"secs":5400,"label":"90\u002700"},"id":4373,"altIds":{"opta":"g17073"}},{"gameweek":{"id":430,"gameweek":34},"kickoff":{"completeness":3,"millis":1050760800000,"label":"Sat 19 Apr 2003, 15:00 BST","gmtOffset":1.0},"provisionalKickoff":{"completeness":0},"teams":[{"team":{"name":"Fulham","club":{"name":"Fulham","shortName":"Fulham","abbr":"FUL","id":34},"teamType":"FIRST","shortName":"Fulham","id":34,"altIds":{"opta":"t54"}},"score":2},{"team":{"name":"Newcastle United","club":{"name":"Newcastle United","shortName":"Newcastle","abbr":"NEW","id":23},"teamType":"FIRST","shortName":"Newcastle","id":23,"altIds":{"opta":"t4"}},"score":1}],"replay":false,"ground":{"name":"Loftus Road","city":"London","source":"OPTA","id":23},"neutralGround":false,"status":"C","phase":"F","outcome":"H","attendance":17900,"clock":{"secs":5400,"label":"90\u002700"},"id":4382,"altIds":{"opta":"g16045"}}],"ground":{"name":"St. James\u0027 Park","city":"Newcastle","capacity":52387,"location":{"latitude":54.9752,"longitude":-1.62235},"source":"OPTA","id":21}},{"team":{"name":"Chelsea","club":{"name":"Chelsea","shortName":"Chelsea","abbr":"CHE","id":4},"teamType":"FIRST","shortName":"Chelsea","id":4,"altIds":{"opta":"t8"}},"position":4,"startingPosition":4,"overall":{"played":34,"won":17,"drawn":9,"lost":8,"goalsFor":61,"goalsAgainst":34,"goalsDifference":27,"points":60},"home":{"played":16,"won":10,"drawn":4,"lost":2,"goalsFor":34,"goalsAgainst":12,"goalsDifference":22,"points":34,"position":5},"away":{"played":18,"won":7,"drawn":5,"lost":6,"goalsFor":27,"goalsAgainst":22,"goalsDifference":5,"points":26,"position":3},"annotations":[{"type":"Q","destination":"EU_CL"}],"form":[{"gameweek":{"id":426,"gameweek":30},"kickoff":{"completeness":3,"millis":1047830700000,"label":"Sun 16 Mar 2003, 16:05 GMT"},"provisionalKickoff":{"completeness":0},"teams":[{"team":{"name":"West Bromwich Albion","club":{"name":"West Bromwich Albion","shortName":"West Brom","abbr":"WBA","id":36},"teamType":"FIRST","shortName":"West Brom","id":36,"altIds":{"opta":"t35"}},"score":0},{"team":{"name":"Chelsea","club":{"name":"Chelsea","shortName":"Chelsea","abbr":"CHE","id":4},"teamType":"FIRST","shortName":"Chelsea","id":4,"altIds":{"opta":"t8"}},"score":2}],"replay":false,"ground":{"name":"The Hawthorns","city":"West Bromwich","source":"OPTA","id":12},"neutralGround":false,"status":"C","phase":"F","outcome":"A","attendance":27024,"clock":{"secs":5400,"label":"90\u002700"},"id":4346,"altIds":{"opta":"g15194"}},{"gameweek":{"id":427,"gameweek":31},"kickoff":{"completeness":3,"millis":1048345200000,"label":"Sat 22 Mar 2003, 15:00 GMT"},"provisionalKickoff":{"completeness":0},"teams":[{"team":{"name":"Chelsea","club":{"name":"Chelsea","shortName":"Chelsea","abbr":"CHE","id":4},"teamType":"FIRST","shortName":"Chelsea","id":4,"altIds":{"opta":"t8"}},"score":5},{"team":{"name":"Manchester City","club":{"name":"Manchester City","shortName":"Man City","abbr":"MCI","id":11},"teamType":"FIRST","shortName":"Man City","id":11,"altIds":{"opta":"t43"}},"score":0}],"replay":false,"ground":{"name":"Stamford Bridge","city":"London","source":"OPTA","id":8},"neutralGround":false,"status":"C","phase":"F","outcome":"H","attendance":41105,"clock":{"secs":5400,"label":"90\u002700"},"id":4348,"altIds":{"opta":"g15195"}},{"gameweek":{"id":428,"gameweek":32},"kickoff":{"completeness":3,"millis":1049551200000,"label":"Sat 5 Apr 2003, 15:00 BST","gmtOffset":1.0},"provisionalKickoff":{"completeness":0},"teams":[{"team":{"name":"Sunderland","club":{"name":"Sunderland","shortName":"Sunderland","abbr":"SUN","id":29},"teamType":"FIRST","shortName":"Sunderland","id":29,"altIds":{"opta":"t56"}},"score":1},{"team":{"name":"Chelsea","club":{"name":"Chelsea","shortName":"Chelsea","abbr":"CHE","id":4},"teamType":"FIRST","shortName":"Chelsea","id":4,"altIds":{"opta":"t8"}},"score":2}],"replay":false,"ground":{"name":"Stadium of Light","city":"Sunderland","source":"OPTA","id":17},"neutralGround":false,"status":"C","phase":"F","outcome":"A","attendance":40011,"clock":{"secs":5400,"label":"90\u002700"},"id":4363,"altIds":{"opta":"g15196"}},{"gameweek":{"id":429,"gameweek":33},"kickoff":{"completeness":3,"millis":1050156000000,"label":"Sat 12 Apr 2003, 15:00 BST","gmtOffset":1.0},"provisionalKickoff":{"completeness":0},"teams":[{"team":{"name":"Chelsea","club":{"name":"Chelsea","shortName":"Chelsea","abbr":"CHE","id":4},"teamType":"FIRST","shortName":"Chelsea","id":4,"altIds":{"opta":"t8"}},"score":1},{"team":{"name":"Bolton Wanderers","club":{"name":"Bolton Wanderers","shortName":"Bolton","abbr":"BOL","id":27},"teamType":"FIRST","shortName":"Bolton","id":27,"altIds":{"opta":"t30"}},"score":0}],"replay":false,"ground":{"name":"Stamford Bridge","city":"London","source":"OPTA","id":8},"neutralGround":false,"status":"C","phase":"F","outcome":"H","attendance":39852,"clock":{"secs":5400,"label":"90\u002700"},"id":4369,"altIds":{"opta":"g14661"}},{"gameweek":{"id":430,"gameweek":34},"kickoff":{"completeness":3,"millis":1050760800000,"label":"Sat 19 Apr 2003, 15:00 BST","gmtOffset":1.0},"provisionalKickoff":{"completeness":0},"teams":[{"team":{"name":"Aston Villa","club":{"name":"Aston Villa","shortName":"Aston Villa","abbr":"AVL","id":2},"teamType":"FIRST","shortName":"Aston Villa","id":2,"altIds":{"opta":"t7"}},"score":2},{"team":{"name":"Chelsea","club":{"name":"Chelsea","shortName":"Chelsea","abbr":"CHE","id":4},"teamType":"FIRST","shortName":"Chelsea","id":4,"altIds":{"opta":"t8"}},"score":1}],"replay":false,"ground":{"name":"Villa Park","city":"Birmingham","source":"OPTA","id":7},"neutralGround":false,"status":"C","phase":"F","outcome":"H","attendance":39358,"clock":{"secs":5400,"label":"90\u002700"},"id":4378,"altIds":{"opta":"g14153"}}],"ground":{"name":"Stamford Bridge","city":"London","capacity":41837,"location":{"latitude":51.4816,"longitude":-0.191016},"source":"OPTA","id":8}},{"team":{"name":"Liverpool","club":{"name":"Liverpool","shortName":"Liverpool","abbr":"LIV","id":10},"teamType":"FIRST","shortName":"Liverpool","id":10,"altIds":{"opta":"t14"}},"position":5,"startingPosition":6,"overall":{"played":34,"won":16,"drawn":10,"lost":8,"goalsFor":51,"goalsAgainst":36,"goalsDifference":15,"points":58},"home":{"played":17,"won":8,"drawn":8,"lost":1,"goalsFor":27,"goalsAgainst":13,"goalsDifference":14,"points":32,"position":9},"away":{"played":17,"won":8,"drawn":2,"lost":7,"goalsFor":24,"goalsAgainst":23,"goalsDifference":1,"points":26,"position":4},"annotations":[{"type":"Q","destination":"EU_UC"}],"form":[{"gameweek":{"id":426,"gameweek":30},"kickoff":{"completeness":3,"millis":1047826800000,"label":"Sun 16 Mar 2003, 15:00 GMT"},"provisionalKickoff":{"completeness":0},"teams":[{"team":{"name":"Tottenham Hotspur","club":{"name":"Tottenham Hotspur","shortName":"Spurs","abbr":"TOT","id":21},"teamType":"FIRST","shortName":"Spurs","id":21,"altIds":{"opta":"t6"}},"score":2},{"team":{"name":"Liverpool","club":{"name":"Liverpool","shortName":"Liverpool","abbr":"LIV","id":10},"teamType":"FIRST","shortName":"Liverpool","id":10,"altIds":{"opta":"t14"}},"score":3}],"replay":false,"ground":{"name":"White Hart Lane","city":"London","source":"OPTA","id":6},"neutralGround":false,"status":"C","phase":"F","outcome":"A","attendance":36077,"clock":{"secs":5400,"label":"90\u002700"},"id":4345,"altIds":{"opta":"g16775"}},{"gameweek":{"id":427,"gameweek":31},"kickoff":{"completeness":3,"millis":1048428000000,"label":"Sun 23 Mar 2003, 14:00 GMT"},"provisionalKickoff":{"completeness":0},"teams":[{"team":{"name":"Liverpool","club":{"name":"Liverpool","shortName":"Liverpool","abbr":"LIV","id":10},"teamType":"FIRST","shortName":"Liverpool","id":10,"altIds":{"opta":"t14"}},"score":3},{"team":{"name":"Leeds United","club":{"name":"Leeds United","shortName":"Leeds","abbr":"LEE","id":9},"teamType":"FIRST","shortName":"Leeds","id":9,"altIds":{"opta":"t2"}},"score":1}],"replay":false,"ground":{"name":"Anfield","city":"Liverpool","source":"OPTA","id":10},"neutralGround":false,"status":"C","phase":"F","outcome":"H","attendance":43021,"clock":{"secs":5400,"label":"90\u002700"},"id":4355,"altIds":{"opta":"g16423"}},{"gameweek":{"id":428,"gameweek":32},"kickoff":{"completeness":3,"millis":1049542200000,"label":"Sat 5 Apr 2003, 12:30 BST","gmtOffset":1.0},"provisionalKickoff":{"completeness":0},"teams":[{"team":{"name":"Manchester United","club":{"name":"Manchester United","shortName":"Man Utd","abbr":"MUN","id":12},"teamType":"FIRST","shortName":"Man Utd","id":12,"altIds":{"opta":"t1"}},"score":4},{"team":{"name":"Liverpool","club":{"name":"Liverpool","shortName":"Liverpool","abbr":"LIV","id":10},"teamType":"FIRST","shortName":"Liverpool","id":10,"altIds":{"opta":"t14"}},"score":0}],"replay":false,"ground":{"name":"Old Trafford","city":"Manchester","source":"OPTA","id":3},"neutralGround":false,"status":"C","phase":"F","outcome":"H","attendance":67639,"clock":{"secs":5400,"label":"90\u002700"},"id":4360,"altIds":{"opta":"g16776"}},{"gameweek":{"id":429,"gameweek":33},"kickoff":{"completeness":3,"millis":1050156000000,"label":"Sat 12 Apr 2003, 15:00 BST","gmtOffset":1.0},"provisionalKickoff":{"completeness":0},"teams":[{"team":{"name":"Liverpool","club":{"name":"Liverpool","shortName":"Liverpool","abbr":"LIV","id":10},"teamType":"FIRST","shortName":"Liverpool","id":10,"altIds":{"opta":"t14"}},"score":2},{"team":{"name":"Fulham","club":{"name":"Fulham","shortName":"Fulham","abbr":"FUL","id":34},"teamType":"FIRST","shortName":"Fulham","id":34,"altIds":{"opta":"t54"}},"score":0}],"replay":false,"ground":{"name":"Anfield","city":"Liverpool","source":"OPTA","id":10},"neutralGround":false,"status":"C","phase":"F","outcome":"H","attendance":42120,"clock":{"secs":5400,"label":"90\u002700"},"id":4371,"altIds":{"opta":"g16044"}},{"gameweek":{"id":430,"gameweek":34},"kickoff":{"completeness":3,"millis":1050760800000,"label":"Sat 19 Apr 2003, 15:00 BST","gmtOffset":1.0},"provisionalKickoff":{"completeness":0},"teams":[{"team":{"name":"Everton","club":{"name":"Everton","shortName":"Everton","abbr":"EVE","id":7},"teamType":"FIRST","shortName":"Everton","id":7,"altIds":{"opta":"t11"}},"score":1},{"team":{"name":"Liverpool","club":{"name":"Liverpool","shortName":"Liverpool","abbr":"LIV","id":10},"teamType":"FIRST","shortName":"Liverpool","id":10,"altIds":{"opta":"t14"}},"score":2}],"replay":false,"ground":{"name":"Goodison Park","city":"Liverpool","source":"OPTA","id":9},"neutralGround":false,"status":"C","phase":"F","outcome":"A","attendance":40162,"clock":{"secs":5400,"label":"90\u002700"},"id":4381,"altIds":{"opta":"g16000"}}],"ground":{"name":"Anfield","city":"Liverpool","capacity":45276,"location":{"latitude":53.4313,"longitude":-2.96158},"source":"OPTA","id":10}},{"team":{"name":"Everton","club":{"name":"Everton","shortName":"Everton","abbr":"EVE","id":7},"teamType":"FIRST","shortName":"Everton","id":7,"altIds":{"opta":"t11"}},"position":6,"startingPosition":5,"overall":{"played":34,"won":16,"drawn":8,"lost":10,"goalsFor":44,"goalsAgainst":40,"goalsDifference":4,"points":56},"home":{"played":17,"won":10,"drawn":5,"lost":2,"goalsFor":25,"goalsAgainst":16,"goalsDifference":9,"points":35,"position":4},"away":{"played":17,"won":6,"drawn":3,"lost":8,"goalsFor":19,"goalsAgainst":24,"goalsDifference":-5,"points":21,"position":6},"annotations":[{"type":"Q","destination":"EU_UC"}],"form":[{"gameweek":{"id":426,"gameweek":30},"kickoff":{"completeness":3,"millis":1047740400000,"label":"Sat 15 Mar 2003, 15:00 GMT"},"provisionalKickoff":{"completeness":0},"teams":[{"team":{"name":"Everton","club":{"name":"Everton","shortName":"Everton","abbr":"EVE","id":7},"teamType":"FIRST","shortName":"Everton","id":7,"altIds":{"opta":"t11"}},"score":0},{"team":{"name":"West Ham United","club":{"name":"West Ham United","shortName":"West Ham","abbr":"WHU","id":25},"teamType":"FIRST","shortName":"West Ham","id":25,"altIds":{"opta":"t21"}},"score":0}],"replay":false,"ground":{"name":"Goodison Park","city":"Liverpool","source":"OPTA","id":9},"neutralGround":false,"status":"C","phase":"F","outcome":"D","attendance":40158,"clock":{"secs":5400,"label":"90\u002700"},"id":4340,"altIds":{"opta":"g15997"}},{"gameweek":{"id":427,"gameweek":31},"kickoff":{"completeness":3,"millis":1048435500000,"label":"Sun 23 Mar 2003, 16:05 GMT"},"provisionalKickoff":{"completeness":0},"teams":[{"team":{"name":"Arsenal","club":{"name":"Arsenal","shortName":"Arsenal","abbr":"ARS","id":1},"teamType":"FIRST","shortName":"Arsenal","id":1,"altIds":{"opta":"t3"}},"score":2},{"team":{"name":"Everton","club":{"name":"Everton","shortName":"Everton","abbr":"EVE","id":7},"teamType":"FIRST","shortName":"Everton","id":7,"altIds":{"opta":"t11"}},"score":1}],"replay":false,"ground":{"name":"Highbury","city":"London","source":"OPTA","id":302},"neutralGround":false,"status":"C","phase":"F","outcome":"H","attendance":38042,"clock":{"secs":5400,"label":"90\u002700"},"id":4354,"altIds":{"opta":"g13742"}},{"gameweek":{"id":428,"gameweek":32},"kickoff":{"completeness":3,"millis":1049641200000,"label":"Sun 6 Apr 2003, 16:00 BST","gmtOffset":1.0},"provisionalKickoff":{"completeness":0},"teams":[{"team":{"name":"Everton","club":{"name":"Everton","shortName":"Everton","abbr":"EVE","id":7},"teamType":"FIRST","shortName":"Everton","id":7,"altIds":{"opta":"t11"}},"score":2},{"team":{"name":"Newcastle United","club":{"name":"Newcastle United","shortName":"Newcastle","abbr":"NEW","id":23},"teamType":"FIRST","shortName":"Newcastle","id":23,"altIds":{"opta":"t4"}},"score":1}],"replay":false,"ground":{"name":"Goodison Park","city":"Liverpool","source":"OPTA","id":9},"neutralGround":false,"status":"C","phase":"F","outcome":"H","attendance":40031,"clock":{"secs":5400,"label":"90\u002700"},"id":4365,"altIds":{"opta":"g15998"}},{"gameweek":{"id":429,"gameweek":33},"kickoff":{"completeness":3,"millis":1050156000000,"label":"Sat 12 Apr 2003, 15:00 BST","gmtOffset":1.0},"provisionalKickoff":{"completeness":0},"teams":[{"team":{"name":"West Bromwich Albion","club":{"name":"West Bromwich Albion","shortName":"West Brom","abbr":"WBA","id":36},"teamType":"FIRST","shortName":"West Brom","id":36,"altIds":{"opta":"t35"}},"score":1},{"team":{"name":"Everton","club":{"name":"Everton","shortName":"Everton","abbr":"EVE","id":7},"teamType":"FIRST","shortName":"Everton","id":7,"altIds":{"opta":"t11"}},"score":2}],"replay":false,"ground":{"name":"The Hawthorns","city":"West Bromwich","source":"OPTA","id":12},"neutralGround":false,"status":"C","phase":"F","outcome":"A","attendance":27039,"clock":{"secs":5400,"label":"90\u002700"},"id":4374,"altIds":{"opta":"g15999"}},{"gameweek":{"id":430,"gameweek":34},"kickoff":{"completeness":3,"millis":1050760800000,"label":"Sat 19 Apr 2003, 15:00 BST","gmtOffset":1.0},"provisionalKickoff":{"completeness":0},"teams":[{"team":{"name":"Everton","club":{"name":"Everton","shortName":"Everton","abbr":"EVE","id":7},"teamType":"FIRST","shortName":"Everton","id":7,"altIds":{"opta":"t11"}},"score":1},{"team":{"name":"Liverpool","club":{"name":"Liverpool","shortName":"Liverpool","abbr":"LIV","id":10},"teamType":"FIRST","shortName":"Liverpool","id":10,"altIds":{"opta":"t14"}},"score":2}],"replay":false,"ground":{"name":"Goodison Park","city":"Liverpool","source":"OPTA","id":9},"neutralGround":false,"status":"C","phase":"F","outcome":"A","attendance":40162,"clock":{"secs":5400,"label":"90\u002700"},"id":4381,"altIds":{"opta":"g16000"}}],"ground":{"name":"Goodison Park","city":"Liverpool","capacity":40157,"location":{"latitude":53.4387,"longitude":-2.96639},"source":"OPTA","id":9}},{"team":{"name":"Blackburn Rovers","club":{"name":"Blackburn Rovers","shortName":"Blackburn","abbr":"BLB","id":3},"teamType":"FIRST","shortName":"Blackburn","id":3,"altIds":{"opta":"t5"}},"position":7,"startingPosition":7,"overall":{"played":34,"won":14,"drawn":10,"lost":10,"goalsFor":44,"goalsAgainst":40,"goalsDifference":4,"points":52},"home":{"played":17,"won":9,"drawn":5,"lost":3,"goalsFor":23,"goalsAgainst":14,"goalsDifference":9,"points":32,"position":11},"away":{"played":17,"won":5,"drawn":5,"lost":7,"goalsFor":21,"goalsAgainst":26,"goalsDifference":-5,"points":20,"position":8},"form":[{"gameweek":{"id":426,"gameweek":30},"kickoff":{"completeness":3,"millis":1047740400000,"label":"Sat 15 Mar 2003, 15:00 GMT"},"provisionalKickoff":{"completeness":0},"teams":[{"team":{"name":"Blackburn Rovers","club":{"name":"Blackburn Rovers","shortName":"Blackburn","abbr":"BLB","id":3},"teamType":"FIRST","shortName":"Blackburn","id":3,"altIds":{"opta":"t5"}},"score":2},{"team":{"name":"Arsenal","club":{"name":"Arsenal","shortName":"Arsenal","abbr":"ARS","id":1},"teamType":"FIRST","shortName":"Arsenal","id":1,"altIds":{"opta":"t3"}},"score":0}],"replay":false,"ground":{"name":"Ewood Park","city":"Blackburn","source":"OPTA","id":5},"neutralGround":false,"status":"C","phase":"F","outcome":"H","attendance":29840,"clock":{"secs":5400,"label":"90\u002700"},"id":4338,"altIds":{"opta":"g13741"}},{"gameweek":{"id":427,"gameweek":31},"kickoff":{"completeness":3,"millis":1048345200000,"label":"Sat 22 Mar 2003, 15:00 GMT"},"provisionalKickoff":{"completeness":0},"teams":[{"team":{"name":"Newcastle United","club":{"name":"Newcastle United","shortName":"Newcastle","abbr":"NEW","id":23},"teamType":"FIRST","shortName":"Newcastle","id":23,"altIds":{"opta":"t4"}},"score":5},{"team":{"name":"Blackburn Rovers","club":{"name":"Blackburn Rovers","shortName":"Blackburn","abbr":"BLB","id":3},"teamType":"FIRST","shortName":"Blackburn","id":3,"altIds":{"opta":"t5"}},"score":1}],"replay":false,"ground":{"name":"St. James\u0027 Park","city":"Newcastle","source":"OPTA","id":21},"neutralGround":false,"status":"C","phase":"F","outcome":"H","attendance":52106,"clock":{"secs":5400,"label":"90\u002700"},"id":4351,"altIds":{"opta":"g14533"}},{"gameweek":{"id":428,"gameweek":32},"kickoff":{"completeness":3,"millis":1049742000000,"label":"Mon 7 Apr 2003, 20:00 BST","gmtOffset":1.0},"provisionalKickoff":{"completeness":0},"teams":[{"team":{"name":"Fulham","club":{"name":"Fulham","shortName":"Fulham","abbr":"FUL","id":34},"teamType":"FIRST","shortName":"Fulham","id":34,"altIds":{"opta":"t54"}},"score":0},{"team":{"name":"Blackburn Rovers","club":{"name":"Blackburn Rovers","shortName":"Blackburn","abbr":"BLB","id":3},"teamType":"FIRST","shortName":"Blackburn","id":3,"altIds":{"opta":"t5"}},"score":4}],"replay":false,"ground":{"name":"Loftus Road","city":"London","source":"OPTA","id":23},"neutralGround":false,"status":"C","phase":"F","outcome":"A","attendance":14017,"clock":{"secs":5400,"label":"90\u002700"},"id":4366,"altIds":{"opta":"g14534"}},{"gameweek":{"id":429,"gameweek":33},"kickoff":{"completeness":3,"millis":1050156000000,"label":"Sat 12 Apr 2003, 15:00 BST","gmtOffset":1.0},"provisionalKickoff":{"completeness":0},"teams":[{"team":{"name":"Blackburn Rovers","club":{"name":"Blackburn Rovers","shortName":"Blackburn","abbr":"BLB","id":3},"teamType":"FIRST","shortName":"Blackburn","id":3,"altIds":{"opta":"t5"}},"score":1},{"team":{"name":"Charlton Athletic","club":{"name":"Charlton Athletic","shortName":"Charlton","abbr":"CHA","id":31},"teamType":"FIRST","shortName":"Charlton","id":31,"altIds":{"opta":"t33"}},"score":0}],"replay":false,"ground":{"name":"Ewood Park","city":"Blackburn","source":"OPTA","id":5},"neutralGround":false,"status":"C","phase":"F","outcome":"H","attendance":27506,"clock":{"secs":5400,"label":"90\u002700"},"id":4368,"altIds":{"opta":"g14535"}},{"gameweek":{"id":430,"gameweek":34},"kickoff":{"completeness":3,"millis":1050760800000,"label":"Sat 19 Apr 2003, 15:00 BST","gmtOffset":1.0},"provisionalKickoff":{"completeness":0},"teams":[{"team":{"name":"Manchester United","club":{"name":"Manchester United","shortName":"Man Utd","abbr":"MUN","id":12},"teamType":"FIRST","shortName":"Man Utd","id":12,"altIds":{"opta":"t1"}},"score":3},{"team":{"name":"Blackburn Rovers","club":{"name":"Blackburn Rovers","shortName":"Blackburn","abbr":"BLB","id":3},"teamType":"FIRST","shortName":"Blackburn","id":3,"altIds":{"opta":"t5"}},"score":1}],"replay":false,"ground":{"name":"Old Trafford","city":"Manchester","source":"OPTA","id":3},"neutralGround":false,"status":"C","phase":"F","outcome":"H","attendance":67626,"clock":{"secs":5400,"label":"90\u002700"},"id":4383,"altIds":{"opta":"g14536"}}],"ground":{"name":"Ewood Park","city":"Blackburn","capacity":31367,"location":{"latitude":53.7286,"longitude":-2.48941},"source":"OPTA","id":5}},{"team":{"name":"Southampton","club":{"name":"Southampton","shortName":"Southampton","abbr":"SOU","id":20},"teamType":"FIRST","shortName":"Southampton","id":20,"altIds":{"opta":"t20"}},"position":8,"startingPosition":11,"overall":{"played":33,"won":12,"drawn":12,"lost":9,"goalsFor":38,"goalsAgainst":35,"goalsDifference":3,"points":48},"home":{"played":18,"won":9,"drawn":7,"lost":2,"goalsFor":25,"goalsAgainst":16,"goalsDifference":9,"points":34,"position":7},"away":{"played":15,"won":3,"drawn":5,"lost":7,"goalsFor":13,"goalsAgainst":19,"goalsDifference":-6,"points":14,"position":14},"annotations":[{"type":"Q","destination":"EU_UC"}],"form":[{"gameweek":{"id":425,"gameweek":29},"kickoff":{"completeness":3,"millis":1046530800000,"label":"Sat 1 Mar 2003, 15:00 GMT"},"provisionalKickoff":{"completeness":0},"teams":[{"team":{"name":"Southampton","club":{"name":"Southampton","shortName":"Southampton","abbr":"SOU","id":20},"teamType":"FIRST","shortName":"Southampton","id":20,"altIds":{"opta":"t20"}},"score":1},{"team":{"name":"West Bromwich Albion","club":{"name":"West Bromwich Albion","shortName":"West Brom","abbr":"WBA","id":36},"teamType":"FIRST","shortName":"West Brom","id":36,"altIds":{"opta":"t35"}},"score":0}],"replay":false,"ground":{"name":"St. Mary\u0027s Stadium","city":"Southampton","source":"OPTA","id":25},"neutralGround":false,"status":"C","phase":"F","outcome":"H","attendance":31915,"clock":{"secs":5400,"label":"90\u002700"},"id":4330,"altIds":{"opta":"g17655"}},{"gameweek":{"id":426,"gameweek":30},"kickoff":{"completeness":3,"millis":1047740400000,"label":"Sat 15 Mar 2003, 15:00 GMT"},"provisionalKickoff":{"completeness":0},"teams":[{"team":{"name":"Fulham","club":{"name":"Fulham","shortName":"Fulham","abbr":"FUL","id":34},"teamType":"FIRST","shortName":"Fulham","id":34,"altIds":{"opta":"t54"}},"score":2},{"team":{"name":"Southampton","club":{"name":"Southampton","shortName":"Southampton","abbr":"SOU","id":20},"teamType":"FIRST","shortName":"Southampton","id":20,"altIds":{"opta":"t20"}},"score":2}],"replay":false,"ground":{"name":"Loftus Road","city":"London","source":"OPTA","id":23},"neutralGround":false,"status":"C","phase":"F","outcome":"D","attendance":18031,"clock":{"secs":5400,"label":"90\u002700"},"id":4341,"altIds":{"opta":"g16042"}},{"gameweek":{"id":427,"gameweek":31},"kickoff":{"completeness":3,"millis":1048345200000,"label":"Sat 22 Mar 2003, 15:00 GMT"},"provisionalKickoff":{"completeness":0},"teams":[{"team":{"name":"Southampton","club":{"name":"Southampton","shortName":"Southampton","abbr":"SOU","id":20},"teamType":"FIRST","shortName":"Southampton","id":20,"altIds":{"opta":"t20"}},"score":2},{"team":{"name":"Aston Villa","club":{"name":"Aston Villa","shortName":"Aston Villa","abbr":"AVL","id":2},"teamType":"FIRST","shortName":"Aston Villa","id":2,"altIds":{"opta":"t7"}},"score":2}],"replay":false,"ground":{"name":"St. Mary\u0027s Stadium","city":"Southampton","source":"OPTA","id":25},"neutralGround":false,"status":"C","phase":"F","outcome":"D","attendance":31888,"clock":{"secs":5400,"label":"90\u002700"},"id":4352,"altIds":{"opta":"g14151"}},{"gameweek":{"id":428,"gameweek":32},"kickoff":{"completeness":3,"millis":1049551200000,"label":"Sat 5 Apr 2003, 15:00 BST","gmtOffset":1.0},"provisionalKickoff":{"completeness":0},"teams":[{"team":{"name":"Southampton","club":{"name":"Southampton","shortName":"Southampton","abbr":"SOU","id":20},"teamType":"FIRST","shortName":"Southampton","id":20,"altIds":{"opta":"t20"}},"score":1},{"team":{"name":"West Ham United","club":{"name":"West Ham United","shortName":"West Ham","abbr":"WHU","id":25},"teamType":"FIRST","shortName":"West Ham","id":25,"altIds":{"opta":"t21"}},"score":1}],"replay":false,"ground":{"name":"St. Mary\u0027s Stadium","city":"Southampton","source":"OPTA","id":25},"neutralGround":false,"status":"C","phase":"F","outcome":"D","attendance":31941,"clock":{"secs":5400,"label":"90\u002700"},"id":4362,"altIds":{"opta":"g17656"}},{"gameweek":{"id":430,"gameweek":34},"kickoff":{"completeness":3,"millis":1050760800000,"label":"Sat 19 Apr 2003, 15:00 BST","gmtOffset":1.0},"provisionalKickoff":{"completeness":0},"teams":[{"team":{"name":"Southampton","club":{"name":"Southampton","shortName":"Southampton","abbr":"SOU","id":20},"teamType":"FIRST","shortName":"Southampton","id":20,"altIds":{"opta":"t20"}},"score":3},{"team":{"name":"Leeds United","club":{"name":"Leeds United","shortName":"Leeds","abbr":"LEE","id":9},"teamType":"FIRST","shortName":"Leeds","id":9,"altIds":{"opta":"t2"}},"score":2}],"replay":false,"ground":{"name":"St. Mary\u0027s Stadium","city":"Southampton","source":"OPTA","id":25},"neutralGround":false,"status":"C","phase":"F","outcome":"H","attendance":32032,"clock":{"secs":5400,"label":"90\u002700"},"id":4385,"altIds":{"opta":"g16425"}}],"ground":{"name":"St. Mary\u0027s Stadium","city":"Southampton","capacity":32690,"location":{"latitude":50.9065,"longitude":-1.39082},"source":"OPTA","id":25}},{"team":{"name":"Tottenham Hotspur","club":{"name":"Tottenham Hotspur","shortName":"Spurs","abbr":"TOT","id":21},"teamType":"FIRST","shortName":"Spurs","id":21,"altIds":{"opta":"t6"}},"position":9,"startingPosition":8,"overall":{"played":34,"won":13,"drawn":8,"lost":13,"goalsFor":47,"goalsAgainst":49,"goalsDifference":-2,"points":47},"home":{"played":17,"won":9,"drawn":4,"lost":4,"goalsFor":30,"goalsAgainst":23,"goalsDifference":7,"points":31,"position":12},"away":{"played":17,"won":4,"drawn":4,"lost":9,"goalsFor":17,"goalsAgainst":26,"goalsDifference":-9,"points":16,"position":12},"form":[{"gameweek":{"id":426,"gameweek":30},"kickoff":{"completeness":3,"millis":1047826800000,"label":"Sun 16 Mar 2003, 15:00 GMT"},"provisionalKickoff":{"completeness":0},"teams":[{"team":{"name":"Tottenham Hotspur","club":{"name":"Tottenham Hotspur","shortName":"Spurs","abbr":"TOT","id":21},"teamType":"FIRST","shortName":"Spurs","id":21,"altIds":{"opta":"t6"}},"score":2},{"team":{"name":"Liverpool","club":{"name":"Liverpool","shortName":"Liverpool","abbr":"LIV","id":10},"teamType":"FIRST","shortName":"Liverpool","id":10,"altIds":{"opta":"t14"}},"score":3}],"replay":false,"ground":{"name":"White Hart Lane","city":"London","source":"OPTA","id":6},"neutralGround":false,"status":"C","phase":"F","outcome":"A","attendance":36077,"clock":{"secs":5400,"label":"90\u002700"},"id":4345,"altIds":{"opta":"g16775"}},{"gameweek":{"id":427,"gameweek":31},"kickoff":{"completeness":3,"millis":1048536000000,"label":"Mon 24 Mar 2003, 20:00 GMT"},"provisionalKickoff":{"completeness":0},"teams":[{"team":{"name":"Bolton Wanderers","club":{"name":"Bolton Wanderers","shortName":"Bolton","abbr":"BOL","id":27},"teamType":"FIRST","shortName":"Bolton","id":27,"altIds":{"opta":"t30"}},"score":1},{"team":{"name":"Tottenham Hotspur","club":{"name":"Tottenham Hotspur","shortName":"Spurs","abbr":"TOT","id":21},"teamType":"FIRST","shortName":"Spurs","id":21,"altIds":{"opta":"t6"}},"score":0}],"replay":false,"ground":{"name":"Macron Stadium","city":"Bolton","source":"OPTA","id":62},"neutralGround":false,"status":"C","phase":"F","outcome":"H","attendance":23084,"clock":{"secs":5400,"label":"90\u002700"},"id":4356,"altIds":{"opta":"g14659"}},{"gameweek":{"id":428,"gameweek":32},"kickoff":{"completeness":3,"millis":1049551200000,"label":"Sat 5 Apr 2003, 15:00 BST","gmtOffset":1.0},"provisionalKickoff":{"completeness":0},"teams":[{"team":{"name":"Tottenham Hotspur","club":{"name":"Tottenham Hotspur","shortName":"Spurs","abbr":"TOT","id":21},"teamType":"FIRST","shortName":"Spurs","id":21,"altIds":{"opta":"t6"}},"score":2},{"team":{"name":"Birmingham City","club":{"name":"Birmingham City","shortName":"Birmingham","abbr":"BIR","id":35},"teamType":"FIRST","shortName":"Birmingham","id":35,"altIds":{"opta":"t41"}},"score":1}],"replay":false,"ground":{"name":"White Hart Lane","city":"London","source":"OPTA","id":6},"neutralGround":false,"status":"C","phase":"F","outcome":"H","attendance":36058,"clock":{"secs":5400,"label":"90\u002700"},"id":4364,"altIds":{"opta":"g14219"}},{"gameweek":{"id":429,"gameweek":33},"kickoff":{"completeness":3,"millis":1050156000000,"label":"Sat 12 Apr 2003, 15:00 BST","gmtOffset":1.0},"provisionalKickoff":{"completeness":0},"teams":[{"team":{"name":"Leeds United","club":{"name":"Leeds United","shortName":"Leeds","abbr":"LEE","id":9},"teamType":"FIRST","shortName":"Leeds","id":9,"altIds":{"opta":"t2"}},"score":2},{"team":{"name":"Tottenham Hotspur","club":{"name":"Tottenham Hotspur","shortName":"Spurs","abbr":"TOT","id":21},"teamType":"FIRST","shortName":"Spurs","id":21,"altIds":{"opta":"t6"}},"score":2}],"replay":false,"ground":{"name":"Elland Road","city":"Leeds","source":"OPTA","id":205},"neutralGround":false,"status":"C","phase":"F","outcome":"D","attendance":39560,"clock":{"secs":5400,"label":"90\u002700"},"id":4370,"altIds":{"opta":"g16424"}},{"gameweek":{"id":430,"gameweek":34},"kickoff":{"completeness":3,"millis":1050674400000,"label":"Fri 18 Apr 2003, 15:00 BST","gmtOffset":1.0},"provisionalKickoff":{"completeness":0},"teams":[{"team":{"name":"Tottenham Hotspur","club":{"name":"Tottenham Hotspur","shortName":"Spurs","abbr":"TOT","id":21},"teamType":"FIRST","shortName":"Spurs","id":21,"altIds":{"opta":"t6"}},"score":0},{"team":{"name":"Manchester City","club":{"name":"Manchester City","shortName":"Man City","abbr":"MCI","id":11},"teamType":"FIRST","shortName":"Man City","id":11,"altIds":{"opta":"t43"}},"score":2}],"replay":false,"ground":{"name":"White Hart Lane","city":"London","source":"OPTA","id":6},"neutralGround":false,"status":"C","phase":"F","outcome":"A","attendance":36075,"clock":{"secs":5400,"label":"90\u002700"},"id":4377,"altIds":{"opta":"g16891"}}],"ground":{"name":"White Hart Lane","city":"London","capacity":36230,"location":{"latitude":51.6031,"longitude":-0.0676},"source":"OPTA","id":6}},{"team":{"name":"Middlesbrough","club":{"name":"Middlesbrough","shortName":"Middlesbrough","abbr":"MID","id":13},"teamType":"FIRST","shortName":"Middlesbrough","id":13,"altIds":{"opta":"t25"}},"position":10,"startingPosition":9,"overall":{"played":34,"won":12,"drawn":10,"lost":12,"goalsFor":42,"goalsAgainst":37,"goalsDifference":5,"points":46},"home":{"played":18,"won":9,"drawn":7,"lost":2,"goalsFor":31,"goalsAgainst":20,"goalsDifference":11,"points":34,"position":6},"away":{"played":16,"won":3,"drawn":3,"lost":10,"goalsFor":11,"goalsAgainst":17,"goalsDifference":-6,"points":12,"position":16},"form":[{"gameweek":{"id":426,"gameweek":30},"kickoff":{"completeness":3,"millis":1047740400000,"label":"Sat 15 Mar 2003, 15:00 GMT"},"provisionalKickoff":{"completeness":0},"teams":[{"team":{"name":"Leeds United","club":{"name":"Leeds United","shortName":"Leeds","abbr":"LEE","id":9},"teamType":"FIRST","shortName":"Leeds","id":9,"altIds":{"opta":"t2"}},"score":2},{"team":{"name":"Middlesbrough","club":{"name":"Middlesbrough","shortName":"Middlesbrough","abbr":"MID","id":13},"teamType":"FIRST","shortName":"Middlesbrough","id":13,"altIds":{"opta":"t25"}},"score":3}],"replay":false,"ground":{"name":"Elland Road","city":"Leeds","source":"OPTA","id":205},"neutralGround":false,"status":"C","phase":"F","outcome":"A","attendance":39073,"clock":{"secs":5400,"label":"90\u002700"},"id":4342,"altIds":{"opta":"g16422"}},{"gameweek":{"id":427,"gameweek":31},"kickoff":{"completeness":3,"millis":1048345200000,"label":"Sat 22 Mar 2003, 15:00 GMT"},"provisionalKickoff":{"completeness":0},"teams":[{"team":{"name":"Middlesbrough","club":{"name":"Middlesbrough","shortName":"Middlesbrough","abbr":"MID","id":13},"teamType":"FIRST","shortName":"Middlesbrough","id":13,"altIds":{"opta":"t25"}},"score":1},{"team":{"name":"Charlton Athletic","club":{"name":"Charlton Athletic","shortName":"Charlton","abbr":"CHA","id":31},"teamType":"FIRST","shortName":"Charlton","id":31,"altIds":{"opta":"t33"}},"score":1}],"replay":false,"ground":{"name":"Riverside Stadium","city":"Middlesbrough","source":"OPTA","id":61},"neutralGround":false,"status":"C","phase":"F","outcome":"D","attendance":29080,"clock":{"secs":5400,"label":"90\u002700"},"id":4350,"altIds":{"opta":"g14851"}},{"gameweek":{"id":428,"gameweek":32},"kickoff":{"completeness":3,"millis":1049551200000,"label":"Sat 5 Apr 2003, 15:00 BST","gmtOffset":1.0},"provisionalKickoff":{"completeness":0},"teams":[{"team":{"name":"Middlesbrough","club":{"name":"Middlesbrough","shortName":"Middlesbrough","abbr":"MID","id":13},"teamType":"FIRST","shortName":"Middlesbrough","id":13,"altIds":{"opta":"t25"}},"score":3},{"team":{"name":"West Bromwich Albion","club":{"name":"West Bromwich Albion","shortName":"West Brom","abbr":"WBA","id":36},"teamType":"FIRST","shortName":"West Brom","id":36,"altIds":{"opta":"t35"}},"score":0}],"replay":false,"ground":{"name":"Riverside Stadium","city":"Middlesbrough","source":"OPTA","id":61},"neutralGround":false,"status":"C","phase":"F","outcome":"H","attendance":30187,"clock":{"secs":5400,"label":"90\u002700"},"id":4361,"altIds":{"opta":"g17184"}},{"gameweek":{"id":429,"gameweek":33},"kickoff":{"completeness":3,"millis":1050156000000,"label":"Sat 12 Apr 2003, 15:00 BST","gmtOffset":1.0},"provisionalKickoff":{"completeness":0},"teams":[{"team":{"name":"Manchester City","club":{"name":"Manchester City","shortName":"Man City","abbr":"MCI","id":11},"teamType":"FIRST","shortName":"Man City","id":11,"altIds":{"opta":"t43"}},"score":0},{"team":{"name":"Middlesbrough","club":{"name":"Middlesbrough","shortName":"Middlesbrough","abbr":"MID","id":13},"teamType":"FIRST","shortName":"Middlesbrough","id":13,"altIds":{"opta":"t25"}},"score":0}],"replay":false,"ground":{"name":"Maine Road","city":"Manchester","source":"OPTA","id":305},"neutralGround":false,"status":"C","phase":"F","outcome":"D","attendance":34793,"clock":{"secs":5400,"label":"90\u002700"},"id":4372,"altIds":{"opta":"g16890"}},{"gameweek":{"id":430,"gameweek":34},"kickoff":{"completeness":3,"millis":1050760800000,"label":"Sat 19 Apr 2003, 15:00 BST","gmtOffset":1.0},"provisionalKickoff":{"completeness":0},"teams":[{"team":{"name":"Middlesbrough","club":{"name":"Middlesbrough","shortName":"Middlesbrough","abbr":"MID","id":13},"teamType":"FIRST","shortName":"Middlesbrough","id":13,"altIds":{"opta":"t25"}},"score":0},{"team":{"name":"Arsenal","club":{"name":"Arsenal","shortName":"Arsenal","abbr":"ARS","id":1},"teamType":"FIRST","shortName":"Arsenal","id":1,"altIds":{"opta":"t3"}},"score":2}],"replay":false,"ground":{"name":"Riverside Stadium","city":"Middlesbrough","source":"OPTA","id":61},"neutralGround":false,"status":"C","phase":"F","outcome":"A","attendance":34724,"clock":{"secs":5400,"label":"90\u002700"},"id":4384,"altIds":{"opta":"g13745"}}],"ground":{"name":"Riverside Stadium","city":"Middlesbrough","capacity":34500,"location":{"latitude":54.5781,"longitude":-1.21776},"source":"OPTA","id":61}},{"team":{"name":"Charlton Athletic","club":{"name":"Charlton Athletic","shortName":"Charlton","abbr":"CHA","id":31},"teamType":"FIRST","shortName":"Charlton","id":31,"altIds":{"opta":"t33"}},"position":11,"startingPosition":10,"overall":{"played":34,"won":13,"drawn":7,"lost":14,"goalsFor":41,"goalsAgainst":48,"goalsDifference":-7,"points":46},"home":{"played":17,"won":7,"drawn":3,"lost":7,"goalsFor":24,"goalsAgainst":28,"goalsDifference":-4,"points":24,"position":15},"away":{"played":17,"won":6,"drawn":4,"lost":7,"goalsFor":17,"goalsAgainst":20,"goalsDifference":-3,"points":22,"position":5},"form":[{"gameweek":{"id":426,"gameweek":30},"kickoff":{"completeness":3,"millis":1047740400000,"label":"Sat 15 Mar 2003, 15:00 GMT"},"provisionalKickoff":{"completeness":0},"teams":[{"team":{"name":"Charlton Athletic","club":{"name":"Charlton Athletic","shortName":"Charlton","abbr":"CHA","id":31},"teamType":"FIRST","shortName":"Charlton","id":31,"altIds":{"opta":"t33"}},"score":0},{"team":{"name":"Newcastle United","club":{"name":"Newcastle United","shortName":"Newcastle","abbr":"NEW","id":23},"teamType":"FIRST","shortName":"Newcastle","id":23,"altIds":{"opta":"t4"}},"score":2}],"replay":false,"ground":{"name":"The Valley","city":"London","source":"OPTA","id":63},"neutralGround":false,"status":"C","phase":"F","outcome":"A","attendance":26728,"clock":{"secs":5400,"label":"90\u002700"},"id":4339,"altIds":{"opta":"g14850"}},{"gameweek":{"id":427,"gameweek":31},"kickoff":{"completeness":3,"millis":1048345200000,"label":"Sat 22 Mar 2003, 15:00 GMT"},"provisionalKickoff":{"completeness":0},"teams":[{"team":{"name":"Middlesbrough","club":{"name":"Middlesbrough","shortName":"Middlesbrough","abbr":"MID","id":13},"teamType":"FIRST","shortName":"Middlesbrough","id":13,"altIds":{"opta":"t25"}},"score":1},{"team":{"name":"Charlton Athletic","club":{"name":"Charlton Athletic","shortName":"Charlton","abbr":"CHA","id":31},"teamType":"FIRST","shortName":"Charlton","id":31,"altIds":{"opta":"t33"}},"score":1}],"replay":false,"ground":{"name":"Riverside Stadium","city":"Middlesbrough","source":"OPTA","id":61},"neutralGround":false,"status":"C","phase":"F","outcome":"D","attendance":29080,"clock":{"secs":5400,"label":"90\u002700"},"id":4350,"altIds":{"opta":"g14851"}},{"gameweek":{"id":428,"gameweek":32},"kickoff":{"completeness":3,"millis":1049551200000,"label":"Sat 5 Apr 2003, 15:00 BST","gmtOffset":1.0},"provisionalKickoff":{"completeness":0},"teams":[{"team":{"name":"Charlton Athletic","club":{"name":"Charlton Athletic","shortName":"Charlton","abbr":"CHA","id":31},"teamType":"FIRST","shortName":"Charlton","id":31,"altIds":{"opta":"t33"}},"score":1},{"team":{"name":"Leeds United","club":{"name":"Leeds United","shortName":"Leeds","abbr":"LEE","id":9},"teamType":"FIRST","shortName":"Leeds","id":9,"altIds":{"opta":"t2"}},"score":6}],"replay":false,"ground":{"name":"The Valley","city":"London","source":"OPTA","id":63},"neutralGround":false,"status":"C","phase":"F","outcome":"A","attendance":26274,"clock":{"secs":5400,"label":"90\u002700"},"id":4359,"altIds":{"opta":"g14852"}},{"gameweek":{"id":429,"gameweek":33},"kickoff":{"completeness":3,"millis":1050156000000,"label":"Sat 12 Apr 2003, 15:00 BST","gmtOffset":1.0},"provisionalKickoff":{"completeness":0},"teams":[{"team":{"name":"Blackburn Rovers","club":{"name":"Blackburn Rovers","shortName":"Blackburn","abbr":"BLB","id":3},"teamType":"FIRST","shortName":"Blackburn","id":3,"altIds":{"opta":"t5"}},"score":1},{"team":{"name":"Charlton Athletic","club":{"name":"Charlton Athletic","shortName":"Charlton","abbr":"CHA","id":31},"teamType":"FIRST","shortName":"Charlton","id":31,"altIds":{"opta":"t33"}},"score":0}],"replay":false,"ground":{"name":"Ewood Park","city":"Blackburn","source":"OPTA","id":5},"neutralGround":false,"status":"C","phase":"F","outcome":"H","attendance":27506,"clock":{"secs":5400,"label":"90\u002700"},"id":4368,"altIds":{"opta":"g14535"}},{"gameweek":{"id":430,"gameweek":34},"kickoff":{"completeness":3,"millis":1050760800000,"label":"Sat 19 Apr 2003, 15:00 BST","gmtOffset":1.0},"provisionalKickoff":{"completeness":0},"teams":[{"team":{"name":"Charlton Athletic","club":{"name":"Charlton Athletic","shortName":"Charlton","abbr":"CHA","id":31},"teamType":"FIRST","shortName":"Charlton","id":31,"altIds":{"opta":"t33"}},"score":0},{"team":{"name":"Birmingham City","club":{"name":"Birmingham City","shortName":"Birmingham","abbr":"BIR","id":35},"teamType":"FIRST","shortName":"Birmingham","id":35,"altIds":{"opta":"t41"}},"score":2}],"replay":false,"ground":{"name":"The Valley","city":"London","source":"OPTA","id":63},"neutralGround":false,"status":"C","phase":"F","outcome":"A","attendance":25732,"clock":{"secs":5400,"label":"90\u002700"},"id":4380,"altIds":{"opta":"g14221"}}],"ground":{"name":"The Valley","city":"London","capacity":26875,"location":{"latitude":51.4865,"longitude":0.035877},"source":"OPTA","id":63}},{"team":{"name":"Manchester City","club":{"name":"Manchester City","shortName":"Man City","abbr":"MCI","id":11},"teamType":"FIRST","shortName":"Man City","id":11,"altIds":{"opta":"t43"}},"position":12,"startingPosition":12,"overall":{"played":34,"won":13,"drawn":6,"lost":15,"goalsFor":42,"goalsAgainst":51,"goalsDifference":-9,"points":45},"home":{"played":16,"won":8,"drawn":2,"lost":6,"goalsFor":25,"goalsAgainst":24,"goalsDifference":1,"points":26,"position":13},"away":{"played":18,"won":5,"drawn":4,"lost":9,"goalsFor":17,"goalsAgainst":27,"goalsDifference":-10,"points":19,"position":10},"annotations":[{"type":"Q","destination":"EU_UC"}],"form":[{"gameweek":{"id":426,"gameweek":30},"kickoff":{"completeness":3,"millis":1047823200000,"label":"Sun 16 Mar 2003, 14:00 GMT"},"provisionalKickoff":{"completeness":0},"teams":[{"team":{"name":"Manchester City","club":{"name":"Manchester City","shortName":"Man City","abbr":"MCI","id":11},"teamType":"FIRST","shortName":"Man City","id":11,"altIds":{"opta":"t43"}},"score":1},{"team":{"name":"Birmingham City","club":{"name":"Birmingham City","shortName":"Birmingham","abbr":"BIR","id":35},"teamType":"FIRST","shortName":"Birmingham","id":35,"altIds":{"opta":"t41"}},"score":0}],"replay":false,"ground":{"name":"Maine Road","city":"Manchester","source":"OPTA","id":305},"neutralGround":false,"status":"C","phase":"F","outcome":"H","attendance":34596,"clock":{"secs":5400,"label":"90\u002700"},"id":4344,"altIds":{"opta":"g14217"}},{"gameweek":{"id":427,"gameweek":31},"kickoff":{"completeness":3,"millis":1048345200000,"label":"Sat 22 Mar 2003, 15:00 GMT"},"provisionalKickoff":{"completeness":0},"teams":[{"team":{"name":"Chelsea","club":{"name":"Chelsea","shortName":"Chelsea","abbr":"CHE","id":4},"teamType":"FIRST","shortName":"Chelsea","id":4,"altIds":{"opta":"t8"}},"score":5},{"team":{"name":"Manchester City","club":{"name":"Manchester City","shortName":"Man City","abbr":"MCI","id":11},"teamType":"FIRST","shortName":"Man City","id":11,"altIds":{"opta":"t43"}},"score":0}],"replay":false,"ground":{"name":"Stamford Bridge","city":"London","source":"OPTA","id":8},"neutralGround":false,"status":"C","phase":"F","outcome":"H","attendance":41105,"clock":{"secs":5400,"label":"90\u002700"},"id":4348,"altIds":{"opta":"g15195"}},{"gameweek":{"id":428,"gameweek":32},"kickoff":{"completeness":3,"millis":1049540400000,"label":"Sat 5 Apr 2003, 12:00 BST","gmtOffset":1.0},"provisionalKickoff":{"completeness":0},"teams":[{"team":{"name":"Bolton Wanderers","club":{"name":"Bolton Wanderers","shortName":"Bolton","abbr":"BOL","id":27},"teamType":"FIRST","shortName":"Bolton","id":27,"altIds":{"opta":"t30"}},"score":2},{"team":{"name":"Manchester City","club":{"name":"Manchester City","shortName":"Man City","abbr":"MCI","id":11},"teamType":"FIRST","shortName":"Man City","id":11,"altIds":{"opta":"t43"}},"score":0}],"replay":false,"ground":{"name":"Macron Stadium","city":"Bolton","source":"OPTA","id":62},"neutralGround":false,"status":"C","phase":"F","outcome":"H","attendance":26949,"clock":{"secs":5400,"label":"90\u002700"},"id":4358,"altIds":{"opta":"g14660"}},{"gameweek":{"id":429,"gameweek":33},"kickoff":{"completeness":3,"millis":1050156000000,"label":"Sat 12 Apr 2003, 15:00 BST","gmtOffset":1.0},"provisionalKickoff":{"completeness":0},"teams":[{"team":{"name":"Manchester City","club":{"name":"Manchester City","shortName":"Man City","abbr":"MCI","id":11},"teamType":"FIRST","shortName":"Man City","id":11,"altIds":{"opta":"t43"}},"score":0},{"team":{"name":"Middlesbrough","club":{"name":"Middlesbrough","shortName":"Middlesbrough","abbr":"MID","id":13},"teamType":"FIRST","shortName":"Middlesbrough","id":13,"altIds":{"opta":"t25"}},"score":0}],"replay":false,"ground":{"name":"Maine Road","city":"Manchester","source":"OPTA","id":305},"neutralGround":false,"status":"C","phase":"F","outcome":"D","attendance":34793,"clock":{"secs":5400,"label":"90\u002700"},"id":4372,"altIds":{"opta":"g16890"}},{"gameweek":{"id":430,"gameweek":34},"kickoff":{"completeness":3,"millis":1050674400000,"label":"Fri 18 Apr 2003, 15:00 BST","gmtOffset":1.0},"provisionalKickoff":{"completeness":0},"teams":[{"team":{"name":"Tottenham Hotspur","club":{"name":"Tottenham Hotspur","shortName":"Spurs","abbr":"TOT","id":21},"teamType":"FIRST","shortName":"Spurs","id":21,"altIds":{"opta":"t6"}},"score":0},{"team":{"name":"Manchester City","club":{"name":"Manchester City","shortName":"Man City","abbr":"MCI","id":11},"teamType":"FIRST","shortName":"Man City","id":11,"altIds":{"opta":"t43"}},"score":2}],"replay":false,"ground":{"name":"White Hart Lane","city":"London","source":"OPTA","id":6},"neutralGround":false,"status":"C","phase":"F","outcome":"A","attendance":36075,"clock":{"secs":5400,"label":"90\u002700"},"id":4377,"altIds":{"opta":"g16891"}}],"ground":{"name":"Maine Road","city":"Manchester","source":"OPTA","id":305}},{"team":{"name":"Aston Villa","club":{"name":"Aston Villa","shortName":"Aston Villa","abbr":"AVL","id":2},"teamType":"FIRST","shortName":"Aston Villa","id":2,"altIds":{"opta":"t7"}},"position":13,"startingPosition":14,"overall":{"played":34,"won":11,"drawn":8,"lost":15,"goalsFor":38,"goalsAgainst":41,"goalsDifference":-3,"points":41},"home":{"played":18,"won":10,"drawn":2,"lost":6,"goalsFor":24,"goalsAgainst":14,"goalsDifference":10,"points":32,"position":10},"away":{"played":16,"won":1,"drawn":6,"lost":9,"goalsFor":14,"goalsAgainst":27,"goalsDifference":-13,"points":9,"position":18},"form":[{"gameweek":{"id":426,"gameweek":30},"kickoff":{"completeness":3,"millis":1047731400000,"label":"Sat 15 Mar 2003, 12:30 GMT"},"provisionalKickoff":{"completeness":0},"teams":[{"team":{"name":"Aston Villa","club":{"name":"Aston Villa","shortName":"Aston Villa","abbr":"AVL","id":2},"teamType":"FIRST","shortName":"Aston Villa","id":2,"altIds":{"opta":"t7"}},"score":0},{"team":{"name":"Manchester United","club":{"name":"Manchester United","shortName":"Man Utd","abbr":"MUN","id":12},"teamType":"FIRST","shortName":"Man Utd","id":12,"altIds":{"opta":"t1"}},"score":1}],"replay":false,"ground":{"name":"Villa Park","city":"Birmingham","source":"OPTA","id":7},"neutralGround":false,"status":"C","phase":"F","outcome":"A","attendance":42602,"clock":{"secs":5400,"label":"90\u002700"},"id":4337,"altIds":{"opta":"g14150"}},{"gameweek":{"id":427,"gameweek":31},"kickoff":{"completeness":3,"millis":1048345200000,"label":"Sat 22 Mar 2003, 15:00 GMT"},"provisionalKickoff":{"completeness":0},"teams":[{"team":{"name":"Southampton","club":{"name":"Southampton","shortName":"Southampton","abbr":"SOU","id":20},"teamType":"FIRST","shortName":"Southampton","id":20,"altIds":{"opta":"t20"}},"score":2},{"team":{"name":"Aston Villa","club":{"name":"Aston Villa","shortName":"Aston Villa","abbr":"AVL","id":2},"teamType":"FIRST","shortName":"Aston Villa","id":2,"altIds":{"opta":"t7"}},"score":2}],"replay":false,"ground":{"name":"St. Mary\u0027s Stadium","city":"Southampton","source":"OPTA","id":25},"neutralGround":false,"status":"C","phase":"F","outcome":"D","attendance":31888,"clock":{"secs":5400,"label":"90\u002700"},"id":4352,"altIds":{"opta":"g14151"}},{"gameweek":{"id":428,"gameweek":32},"kickoff":{"completeness":3,"millis":1049551200000,"label":"Sat 5 Apr 2003, 15:00 BST","gmtOffset":1.0},"provisionalKickoff":{"completeness":0},"teams":[{"team":{"name":"Aston Villa","club":{"name":"Aston Villa","shortName":"Aston Villa","abbr":"AVL","id":2},"teamType":"FIRST","shortName":"Aston Villa","id":2,"altIds":{"opta":"t7"}},"score":1},{"team":{"name":"Arsenal","club":{"name":"Arsenal","shortName":"Arsenal","abbr":"ARS","id":1},"teamType":"FIRST","shortName":"Arsenal","id":1,"altIds":{"opta":"t3"}},"score":1}],"replay":false,"ground":{"name":"Villa Park","city":"Birmingham","source":"OPTA","id":7},"neutralGround":false,"status":"C","phase":"F","outcome":"D","attendance":42602,"clock":{"secs":5400,"label":"90\u002700"},"id":4357,"altIds":{"opta":"g13743"}},{"gameweek":{"id":429,"gameweek":33},"kickoff":{"completeness":3,"millis":1050156000000,"label":"Sat 12 Apr 2003, 15:00 BST","gmtOffset":1.0},"provisionalKickoff":{"completeness":0},"teams":[{"team":{"name":"West Ham United","club":{"name":"West Ham United","shortName":"West Ham","abbr":"WHU","id":25},"teamType":"FIRST","shortName":"West Ham","id":25,"altIds":{"opta":"t21"}},"score":2},{"team":{"name":"Aston Villa","club":{"name":"Aston Villa","shortName":"Aston Villa","abbr":"AVL","id":2},"teamType":"FIRST","shortName":"Aston Villa","id":2,"altIds":{"opta":"t7"}},"score":2}],"replay":false,"ground":{"name":"Boleyn Ground","city":"London","source":"OPTA","id":22},"neutralGround":false,"status":"C","phase":"F","outcome":"D","attendance":35029,"clock":{"secs":5400,"label":"90\u002700"},"id":4375,"altIds":{"opta":"g14152"}},{"gameweek":{"id":430,"gameweek":34},"kickoff":{"completeness":3,"millis":1050760800000,"label":"Sat 19 Apr 2003, 15:00 BST","gmtOffset":1.0},"provisionalKickoff":{"completeness":0},"teams":[{"team":{"name":"Aston Villa","club":{"name":"Aston Villa","shortName":"Aston Villa","abbr":"AVL","id":2},"teamType":"FIRST","shortName":"Aston Villa","id":2,"altIds":{"opta":"t7"}},"score":2},{"team":{"name":"Chelsea","club":{"name":"Chelsea","shortName":"Chelsea","abbr":"CHE","id":4},"teamType":"FIRST","shortName":"Chelsea","id":4,"altIds":{"opta":"t8"}},"score":1}],"replay":false,"ground":{"name":"Villa Park","city":"Birmingham","source":"OPTA","id":7},"neutralGround":false,"status":"C","phase":"F","outcome":"H","attendance":39358,"clock":{"secs":5400,"label":"90\u002700"},"id":4378,"altIds":{"opta":"g14153"}}],"ground":{"name":"Villa Park","city":"Birmingham","capacity":42788,"location":{"latitude":52.5085,"longitude":-1.88495},"source":"OPTA","id":7}},{"team":{"name":"Fulham","club":{"name":"Fulham","shortName":"Fulham","abbr":"FUL","id":34},"teamType":"FIRST","shortName":"Fulham","id":34,"altIds":{"opta":"t54"}},"position":14,"startingPosition":15,"overall":{"played":34,"won":11,"drawn":8,"lost":15,"goalsFor":37,"goalsAgainst":47,"goalsDifference":-10,"points":41},"home":{"played":18,"won":10,"drawn":3,"lost":5,"goalsFor":24,"goalsAgainst":18,"goalsDifference":6,"points":33,"position":8},"away":{"played":16,"won":1,"drawn":5,"lost":10,"goalsFor":13,"goalsAgainst":29,"goalsDifference":-16,"points":8,"position":19},"form":[{"gameweek":{"id":426,"gameweek":30},"kickoff":{"completeness":3,"millis":1047740400000,"label":"Sat 15 Mar 2003, 15:00 GMT"},"provisionalKickoff":{"completeness":0},"teams":[{"team":{"name":"Fulham","club":{"name":"Fulham","shortName":"Fulham","abbr":"FUL","id":34},"teamType":"FIRST","shortName":"Fulham","id":34,"altIds":{"opta":"t54"}},"score":2},{"team":{"name":"Southampton","club":{"name":"Southampton","shortName":"Southampton","abbr":"SOU","id":20},"teamType":"FIRST","shortName":"Southampton","id":20,"altIds":{"opta":"t20"}},"score":2}],"replay":false,"ground":{"name":"Loftus Road","city":"London","source":"OPTA","id":23},"neutralGround":false,"status":"C","phase":"F","outcome":"D","attendance":18031,"clock":{"secs":5400,"label":"90\u002700"},"id":4341,"altIds":{"opta":"g16042"}},{"gameweek":{"id":427,"gameweek":31},"kickoff":{"completeness":3,"millis":1048336200000,"label":"Sat 22 Mar 2003, 12:30 GMT"},"provisionalKickoff":{"completeness":0},"teams":[{"team":{"name":"Manchester United","club":{"name":"Manchester United","shortName":"Man Utd","abbr":"MUN","id":12},"teamType":"FIRST","shortName":"Man Utd","id":12,"altIds":{"opta":"t1"}},"score":3},{"team":{"name":"Fulham","club":{"name":"Fulham","shortName":"Fulham","abbr":"FUL","id":34},"teamType":"FIRST","shortName":"Fulham","id":34,"altIds":{"opta":"t54"}},"score":0}],"replay":false,"ground":{"name":"Old Trafford","city":"Manchester","source":"OPTA","id":3},"neutralGround":false,"status":"C","phase":"F","outcome":"H","attendance":67706,"clock":{"secs":5400,"label":"90\u002700"},"id":4349,"altIds":{"opta":"g16043"}},{"gameweek":{"id":428,"gameweek":32},"kickoff":{"completeness":3,"millis":1049742000000,"label":"Mon 7 Apr 2003, 20:00 BST","gmtOffset":1.0},"provisionalKickoff":{"completeness":0},"teams":[{"team":{"name":"Fulham","club":{"name":"Fulham","shortName":"Fulham","abbr":"FUL","id":34},"teamType":"FIRST","shortName":"Fulham","id":34,"altIds":{"opta":"t54"}},"score":0},{"team":{"name":"Blackburn Rovers","club":{"name":"Blackburn Rovers","shortName":"Blackburn","abbr":"BLB","id":3},"teamType":"FIRST","shortName":"Blackburn","id":3,"altIds":{"opta":"t5"}},"score":4}],"replay":false,"ground":{"name":"Loftus Road","city":"London","source":"OPTA","id":23},"neutralGround":false,"status":"C","phase":"F","outcome":"A","attendance":14017,"clock":{"secs":5400,"label":"90\u002700"},"id":4366,"altIds":{"opta":"g14534"}},{"gameweek":{"id":429,"gameweek":33},"kickoff":{"completeness":3,"millis":1050156000000,"label":"Sat 12 Apr 2003, 15:00 BST","gmtOffset":1.0},"provisionalKickoff":{"completeness":0},"teams":[{"team":{"name":"Liverpool","club":{"name":"Liverpool","shortName":"Liverpool","abbr":"LIV","id":10},"teamType":"FIRST","shortName":"Liverpool","id":10,"altIds":{"opta":"t14"}},"score":2},{"team":{"name":"Fulham","club":{"name":"Fulham","shortName":"Fulham","abbr":"FUL","id":34},"teamType":"FIRST","shortName":"Fulham","id":34,"altIds":{"opta":"t54"}},"score":0}],"replay":false,"ground":{"name":"Anfield","city":"Liverpool","source":"OPTA","id":10},"neutralGround":false,"status":"C","phase":"F","outcome":"H","attendance":42120,"clock":{"secs":5400,"label":"90\u002700"},"id":4371,"altIds":{"opta":"g16044"}},{"gameweek":{"id":430,"gameweek":34},"kickoff":{"completeness":3,"millis":1050760800000,"label":"Sat 19 Apr 2003, 15:00 BST","gmtOffset":1.0},"provisionalKickoff":{"completeness":0},"teams":[{"team":{"name":"Fulham","club":{"name":"Fulham","shortName":"Fulham","abbr":"FUL","id":34},"teamType":"FIRST","shortName":"Fulham","id":34,"altIds":{"opta":"t54"}},"score":2},{"team":{"name":"Newcastle United","club":{"name":"Newcastle United","shortName":"Newcastle","abbr":"NEW","id":23},"teamType":"FIRST","shortName":"Newcastle","id":23,"altIds":{"opta":"t4"}},"score":1}],"replay":false,"ground":{"name":"Loftus Road","city":"London","source":"OPTA","id":23},"neutralGround":false,"status":"C","phase":"F","outcome":"H","attendance":17900,"clock":{"secs":5400,"label":"90\u002700"},"id":4382,"altIds":{"opta":"g16045"}}],"ground":{"name":"Loftus Road","city":"London","capacity":18360,"location":{"latitude":51.5097,"longitude":-0.232037},"source":"OPTA","id":23}},{"team":{"name":"Birmingham City","club":{"name":"Birmingham City","shortName":"Birmingham","abbr":"BIR","id":35},"teamType":"FIRST","shortName":"Birmingham","id":35,"altIds":{"opta":"t41"}},"position":15,"startingPosition":16,"overall":{"played":34,"won":11,"drawn":8,"lost":15,"goalsFor":33,"goalsAgainst":44,"goalsDifference":-11,"points":41},"home":{"played":16,"won":6,"drawn":4,"lost":6,"goalsFor":17,"goalsAgainst":19,"goalsDifference":-2,"points":22,"position":16},"away":{"played":18,"won":5,"drawn":4,"lost":9,"goalsFor":16,"goalsAgainst":25,"goalsDifference":-9,"points":19,"position":9},"form":[{"gameweek":{"id":426,"gameweek":30},"kickoff":{"completeness":3,"millis":1047823200000,"label":"Sun 16 Mar 2003, 14:00 GMT"},"provisionalKickoff":{"completeness":0},"teams":[{"team":{"name":"Manchester City","club":{"name":"Manchester City","shortName":"Man City","abbr":"MCI","id":11},"teamType":"FIRST","shortName":"Man City","id":11,"altIds":{"opta":"t43"}},"score":1},{"team":{"name":"Birmingham City","club":{"name":"Birmingham City","shortName":"Birmingham","abbr":"BIR","id":35},"teamType":"FIRST","shortName":"Birmingham","id":35,"altIds":{"opta":"t41"}},"score":0}],"replay":false,"ground":{"name":"Maine Road","city":"Manchester","source":"OPTA","id":305},"neutralGround":false,"status":"C","phase":"F","outcome":"H","attendance":34596,"clock":{"secs":5400,"label":"90\u002700"},"id":4344,"altIds":{"opta":"g14217"}},{"gameweek":{"id":427,"gameweek":31},"kickoff":{"completeness":3,"millis":1048334400000,"label":"Sat 22 Mar 2003, 12:00 GMT"},"provisionalKickoff":{"completeness":0},"teams":[{"team":{"name":"Birmingham City","club":{"name":"Birmingham City","shortName":"Birmingham","abbr":"BIR","id":35},"teamType":"FIRST","shortName":"Birmingham","id":35,"altIds":{"opta":"t41"}},"score":1},{"team":{"name":"West Bromwich Albion","club":{"name":"West Bromwich Albion","shortName":"West Brom","abbr":"WBA","id":36},"teamType":"FIRST","shortName":"West Brom","id":36,"altIds":{"opta":"t35"}},"score":0}],"replay":false,"ground":{"name":"St. Andrew\u0027s Stadium","city":"Birmingham","source":"OPTA","id":67},"neutralGround":false,"status":"C","phase":"F","outcome":"H","attendance":29449,"clock":{"secs":5400,"label":"90\u002700"},"id":4347,"altIds":{"opta":"g14218"}},{"gameweek":{"id":428,"gameweek":32},"kickoff":{"completeness":3,"millis":1049551200000,"label":"Sat 5 Apr 2003, 15:00 BST","gmtOffset":1.0},"provisionalKickoff":{"completeness":0},"teams":[{"team":{"name":"Tottenham Hotspur","club":{"name":"Tottenham Hotspur","shortName":"Spurs","abbr":"TOT","id":21},"teamType":"FIRST","shortName":"Spurs","id":21,"altIds":{"opta":"t6"}},"score":2},{"team":{"name":"Birmingham City","club":{"name":"Birmingham City","shortName":"Birmingham","abbr":"BIR","id":35},"teamType":"FIRST","shortName":"Birmingham","id":35,"altIds":{"opta":"t41"}},"score":1}],"replay":false,"ground":{"name":"White Hart Lane","city":"London","source":"OPTA","id":6},"neutralGround":false,"status":"C","phase":"F","outcome":"H","attendance":36058,"clock":{"secs":5400,"label":"90\u002700"},"id":4364,"altIds":{"opta":"g14219"}},{"gameweek":{"id":429,"gameweek":33},"kickoff":{"completeness":3,"millis":1050156000000,"label":"Sat 12 Apr 2003, 15:00 BST","gmtOffset":1.0},"provisionalKickoff":{"completeness":0},"teams":[{"team":{"name":"Birmingham City","club":{"name":"Birmingham City","shortName":"Birmingham","abbr":"BIR","id":35},"teamType":"FIRST","shortName":"Birmingham","id":35,"altIds":{"opta":"t41"}},"score":2},{"team":{"name":"Sunderland","club":{"name":"Sunderland","shortName":"Sunderland","abbr":"SUN","id":29},"teamType":"FIRST","shortName":"Sunderland","id":29,"altIds":{"opta":"t56"}},"score":0}],"replay":false,"ground":{"name":"St. Andrew\u0027s Stadium","city":"Birmingham","source":"OPTA","id":67},"neutralGround":false,"status":"C","phase":"F","outcome":"H","attendance":29132,"clock":{"secs":5400,"label":"90\u002700"},"id":4367,"altIds":{"opta":"g14220"}},{"gameweek":{"id":430,"gameweek":34},"kickoff":{"completeness":3,"millis":1050760800000,"label":"Sat 19 Apr 2003, 15:00 BST","gmtOffset":1.0},"provisionalKickoff":{"completeness":0},"teams":[{"team":{"name":"Charlton Athletic","club":{"name":"Charlton Athletic","shortName":"Charlton","abbr":"CHA","id":31},"teamType":"FIRST","shortName":"Charlton","id":31,"altIds":{"opta":"t33"}},"score":0},{"team":{"name":"Birmingham City","club":{"name":"Birmingham City","shortName":"Birmingham","abbr":"BIR","id":35},"teamType":"FIRST","shortName":"Birmingham","id":35,"altIds":{"opta":"t41"}},"score":2}],"replay":false,"ground":{"name":"The Valley","city":"London","source":"OPTA","id":63},"neutralGround":false,"status":"C","phase":"F","outcome":"A","attendance":25732,"clock":{"secs":5400,"label":"90\u002700"},"id":4380,"altIds":{"opta":"g14221"}}],"ground":{"name":"St. Andrew\u0027s Stadium","city":"Birmingham","capacity":30009,"location":{"latitude":52.4756,"longitude":-1.86824},"source":"OPTA","id":67}},{"team":{"name":"Leeds United","club":{"name":"Leeds United","shortName":"Leeds","abbr":"LEE","id":9},"teamType":"FIRST","shortName":"Leeds","id":9,"altIds":{"opta":"t2"}},"position":16,"startingPosition":13,"overall":{"played":34,"won":11,"drawn":5,"lost":18,"goalsFor":48,"goalsAgainst":51,"goalsDifference":-3,"points":38},"home":{"played":16,"won":5,"drawn":3,"lost":8,"goalsFor":18,"goalsAgainst":22,"goalsDifference":-4,"points":18,"position":17},"away":{"played":18,"won":6,"drawn":2,"lost":10,"goalsFor":30,"goalsAgainst":29,"goalsDifference":1,"points":20,"position":7},"form":[{"gameweek":{"id":426,"gameweek":30},"kickoff":{"completeness":3,"millis":1047740400000,"label":"Sat 15 Mar 2003, 15:00 GMT"},"provisionalKickoff":{"completeness":0},"teams":[{"team":{"name":"Leeds United","club":{"name":"Leeds United","shortName":"Leeds","abbr":"LEE","id":9},"teamType":"FIRST","shortName":"Leeds","id":9,"altIds":{"opta":"t2"}},"score":2},{"team":{"name":"Middlesbrough","club":{"name":"Middlesbrough","shortName":"Middlesbrough","abbr":"MID","id":13},"teamType":"FIRST","shortName":"Middlesbrough","id":13,"altIds":{"opta":"t25"}},"score":3}],"replay":false,"ground":{"name":"Elland Road","city":"Leeds","source":"OPTA","id":205},"neutralGround":false,"status":"C","phase":"F","outcome":"A","attendance":39073,"clock":{"secs":5400,"label":"90\u002700"},"id":4342,"altIds":{"opta":"g16422"}},{"gameweek":{"id":427,"gameweek":31},"kickoff":{"completeness":3,"millis":1048428000000,"label":"Sun 23 Mar 2003, 14:00 GMT"},"provisionalKickoff":{"completeness":0},"teams":[{"team":{"name":"Liverpool","club":{"name":"Liverpool","shortName":"Liverpool","abbr":"LIV","id":10},"teamType":"FIRST","shortName":"Liverpool","id":10,"altIds":{"opta":"t14"}},"score":3},{"team":{"name":"Leeds United","club":{"name":"Leeds United","shortName":"Leeds","abbr":"LEE","id":9},"teamType":"FIRST","shortName":"Leeds","id":9,"altIds":{"opta":"t2"}},"score":1}],"replay":false,"ground":{"name":"Anfield","city":"Liverpool","source":"OPTA","id":10},"neutralGround":false,"status":"C","phase":"F","outcome":"H","attendance":43021,"clock":{"secs":5400,"label":"90\u002700"},"id":4355,"altIds":{"opta":"g16423"}},{"gameweek":{"id":428,"gameweek":32},"kickoff":{"completeness":3,"millis":1049551200000,"label":"Sat 5 Apr 2003, 15:00 BST","gmtOffset":1.0},"provisionalKickoff":{"completeness":0},"teams":[{"team":{"name":"Charlton Athletic","club":{"name":"Charlton Athletic","shortName":"Charlton","abbr":"CHA","id":31},"teamType":"FIRST","shortName":"Charlton","id":31,"altIds":{"opta":"t33"}},"score":1},{"team":{"name":"Leeds United","club":{"name":"Leeds United","shortName":"Leeds","abbr":"LEE","id":9},"teamType":"FIRST","shortName":"Leeds","id":9,"altIds":{"opta":"t2"}},"score":6}],"replay":false,"ground":{"name":"The Valley","city":"London","source":"OPTA","id":63},"neutralGround":false,"status":"C","phase":"F","outcome":"A","attendance":26274,"clock":{"secs":5400,"label":"90\u002700"},"id":4359,"altIds":{"opta":"g14852"}},{"gameweek":{"id":429,"gameweek":33},"kickoff":{"completeness":3,"millis":1050156000000,"label":"Sat 12 Apr 2003, 15:00 BST","gmtOffset":1.0},"provisionalKickoff":{"completeness":0},"teams":[{"team":{"name":"Leeds United","club":{"name":"Leeds United","shortName":"Leeds","abbr":"LEE","id":9},"teamType":"FIRST","shortName":"Leeds","id":9,"altIds":{"opta":"t2"}},"score":2},{"team":{"name":"Tottenham Hotspur","club":{"name":"Tottenham Hotspur","shortName":"Spurs","abbr":"TOT","id":21},"teamType":"FIRST","shortName":"Spurs","id":21,"altIds":{"opta":"t6"}},"score":2}],"replay":false,"ground":{"name":"Elland Road","city":"Leeds","source":"OPTA","id":205},"neutralGround":false,"status":"C","phase":"F","outcome":"D","attendance":39560,"clock":{"secs":5400,"label":"90\u002700"},"id":4370,"altIds":{"opta":"g16424"}},{"gameweek":{"id":430,"gameweek":34},"kickoff":{"completeness":3,"millis":1050760800000,"label":"Sat 19 Apr 2003, 15:00 BST","gmtOffset":1.0},"provisionalKickoff":{"completeness":0},"teams":[{"team":{"name":"Southampton","club":{"name":"Southampton","shortName":"Southampton","abbr":"SOU","id":20},"teamType":"FIRST","shortName":"Southampton","id":20,"altIds":{"opta":"t20"}},"score":3},{"team":{"name":"Leeds United","club":{"name":"Leeds United","shortName":"Leeds","abbr":"LEE","id":9},"teamType":"FIRST","shortName":"Leeds","id":9,"altIds":{"opta":"t2"}},"score":2}],"replay":false,"ground":{"name":"St. Mary\u0027s Stadium","city":"Southampton","source":"OPTA","id":25},"neutralGround":false,"status":"C","phase":"F","outcome":"H","attendance":32032,"clock":{"secs":5400,"label":"90\u002700"},"id":4385,"altIds":{"opta":"g16425"}}],"ground":{"name":"Elland Road","city":"Leeds","capacity":40000,"location":{"latitude":53.7772,"longitude":-1.57153},"source":"OPTA","id":205}},{"team":{"name":"Bolton Wanderers","club":{"name":"Bolton Wanderers","shortName":"Bolton","abbr":"BOL","id":27},"teamType":"FIRST","shortName":"Bolton","id":27,"altIds":{"opta":"t30"}},"position":17,"startingPosition":17,"overall":{"played":34,"won":9,"drawn":11,"lost":14,"goalsFor":37,"goalsAgainst":48,"goalsDifference":-11,"points":38},"home":{"played":17,"won":6,"drawn":7,"lost":4,"goalsFor":23,"goalsAgainst":21,"goalsDifference":2,"points":25,"position":14},"away":{"played":17,"won":3,"drawn":4,"lost":10,"goalsFor":14,"goalsAgainst":27,"goalsDifference":-13,"points":13,"position":15},"form":[{"gameweek":{"id":426,"gameweek":30},"kickoff":{"completeness":3,"millis":1047740400000,"label":"Sat 15 Mar 2003, 15:00 GMT"},"provisionalKickoff":{"completeness":0},"teams":[{"team":{"name":"Sunderland","club":{"name":"Sunderland","shortName":"Sunderland","abbr":"SUN","id":29},"teamType":"FIRST","shortName":"Sunderland","id":29,"altIds":{"opta":"t56"}},"score":0},{"team":{"name":"Bolton Wanderers","club":{"name":"Bolton Wanderers","shortName":"Bolton","abbr":"BOL","id":27},"teamType":"FIRST","shortName":"Bolton","id":27,"altIds":{"opta":"t30"}},"score":2}],"replay":false,"ground":{"name":"Stadium of Light","city":"Sunderland","source":"OPTA","id":17},"neutralGround":false,"status":"C","phase":"F","outcome":"A","attendance":42124,"clock":{"secs":5400,"label":"90\u002700"},"id":4343,"altIds":{"opta":"g14658"}},{"gameweek":{"id":427,"gameweek":31},"kickoff":{"completeness":3,"millis":1048536000000,"label":"Mon 24 Mar 2003, 20:00 GMT"},"provisionalKickoff":{"completeness":0},"teams":[{"team":{"name":"Bolton Wanderers","club":{"name":"Bolton Wanderers","shortName":"Bolton","abbr":"BOL","id":27},"teamType":"FIRST","shortName":"Bolton","id":27,"altIds":{"opta":"t30"}},"score":1},{"team":{"name":"Tottenham Hotspur","club":{"name":"Tottenham Hotspur","shortName":"Spurs","abbr":"TOT","id":21},"teamType":"FIRST","shortName":"Spurs","id":21,"altIds":{"opta":"t6"}},"score":0}],"replay":false,"ground":{"name":"Macron Stadium","city":"Bolton","source":"OPTA","id":62},"neutralGround":false,"status":"C","phase":"F","outcome":"H","attendance":23084,"clock":{"secs":5400,"label":"90\u002700"},"id":4356,"altIds":{"opta":"g14659"}},{"gameweek":{"id":428,"gameweek":32},"kickoff":{"completeness":3,"millis":1049540400000,"label":"Sat 5 Apr 2003, 12:00 BST","gmtOffset":1.0},"provisionalKickoff":{"completeness":0},"teams":[{"team":{"name":"Bolton Wanderers","club":{"name":"Bolton Wanderers","shortName":"Bolton","abbr":"BOL","id":27},"teamType":"FIRST","shortName":"Bolton","id":27,"altIds":{"opta":"t30"}},"score":2},{"team":{"name":"Manchester City","club":{"name":"Manchester City","shortName":"Man City","abbr":"MCI","id":11},"teamType":"FIRST","shortName":"Man City","id":11,"altIds":{"opta":"t43"}},"score":0}],"replay":false,"ground":{"name":"Macron Stadium","city":"Bolton","source":"OPTA","id":62},"neutralGround":false,"status":"C","phase":"F","outcome":"H","attendance":26949,"clock":{"secs":5400,"label":"90\u002700"},"id":4358,"altIds":{"opta":"g14660"}},{"gameweek":{"id":429,"gameweek":33},"kickoff":{"completeness":3,"millis":1050156000000,"label":"Sat 12 Apr 2003, 15:00 BST","gmtOffset":1.0},"provisionalKickoff":{"completeness":0},"teams":[{"team":{"name":"Chelsea","club":{"name":"Chelsea","shortName":"Chelsea","abbr":"CHE","id":4},"teamType":"FIRST","shortName":"Chelsea","id":4,"altIds":{"opta":"t8"}},"score":1},{"team":{"name":"Bolton Wanderers","club":{"name":"Bolton Wanderers","shortName":"Bolton","abbr":"BOL","id":27},"teamType":"FIRST","shortName":"Bolton","id":27,"altIds":{"opta":"t30"}},"score":0}],"replay":false,"ground":{"name":"Stamford Bridge","city":"London","source":"OPTA","id":8},"neutralGround":false,"status":"C","phase":"F","outcome":"H","attendance":39852,"clock":{"secs":5400,"label":"90\u002700"},"id":4369,"altIds":{"opta":"g14661"}},{"gameweek":{"id":430,"gameweek":34},"kickoff":{"completeness":3,"millis":1050760800000,"label":"Sat 19 Apr 2003, 15:00 BST","gmtOffset":1.0},"provisionalKickoff":{"completeness":0},"teams":[{"team":{"name":"Bolton Wanderers","club":{"name":"Bolton Wanderers","shortName":"Bolton","abbr":"BOL","id":27},"teamType":"FIRST","shortName":"Bolton","id":27,"altIds":{"opta":"t30"}},"score":1},{"team":{"name":"West Ham United","club":{"name":"West Ham United","shortName":"West Ham","abbr":"WHU","id":25},"teamType":"FIRST","shortName":"West Ham","id":25,"altIds":{"opta":"t21"}},"score":0}],"replay":false,"ground":{"name":"Macron Stadium","city":"Bolton","source":"OPTA","id":62},"neutralGround":false,"status":"C","phase":"F","outcome":"H","attendance":27160,"clock":{"secs":5400,"label":"90\u002700"},"id":4379,"altIds":{"opta":"g14662"}}],"ground":{"name":"Macron Stadium","city":"Bolton","capacity":28000,"location":{"latitude":53.5803,"longitude":-2.53615},"source":"OPTA","id":62}},{"team":{"name":"West Ham United","club":{"name":"West Ham United","shortName":"West Ham","abbr":"WHU","id":25},"teamType":"FIRST","shortName":"West Ham","id":25,"altIds":{"opta":"t21"}},"position":18,"startingPosition":18,"overall":{"played":34,"won":7,"drawn":11,"lost":16,"goalsFor":37,"goalsAgainst":57,"goalsDifference":-20,"points":32},"home":{"played":17,"won":3,"drawn":7,"lost":7,"goalsFor":19,"goalsAgainst":24,"goalsDifference":-5,"points":16,"position":18},"away":{"played":17,"won":4,"drawn":4,"lost":9,"goalsFor":18,"goalsAgainst":33,"goalsDifference":-15,"points":16,"position":13},"annotations":[{"type":"R","destination":"EN_D1"}],"form":[{"gameweek":{"id":426,"gameweek":30},"kickoff":{"completeness":3,"millis":1047740400000,"label":"Sat 15 Mar 2003, 15:00 GMT"},"provisionalKickoff":{"completeness":0},"teams":[{"team":{"name":"Everton","club":{"name":"Everton","shortName":"Everton","abbr":"EVE","id":7},"teamType":"FIRST","shortName":"Everton","id":7,"altIds":{"opta":"t11"}},"score":0},{"team":{"name":"West Ham United","club":{"name":"West Ham United","shortName":"West Ham","abbr":"WHU","id":25},"teamType":"FIRST","shortName":"West Ham","id":25,"altIds":{"opta":"t21"}},"score":0}],"replay":false,"ground":{"name":"Goodison Park","city":"Liverpool","source":"OPTA","id":9},"neutralGround":false,"status":"C","phase":"F","outcome":"D","attendance":40158,"clock":{"secs":5400,"label":"90\u002700"},"id":4340,"altIds":{"opta":"g15997"}},{"gameweek":{"id":427,"gameweek":31},"kickoff":{"completeness":3,"millis":1048345200000,"label":"Sat 22 Mar 2003, 15:00 GMT"},"provisionalKickoff":{"completeness":0},"teams":[{"team":{"name":"West Ham United","club":{"name":"West Ham United","shortName":"West Ham","abbr":"WHU","id":25},"teamType":"FIRST","shortName":"West Ham","id":25,"altIds":{"opta":"t21"}},"score":2},{"team":{"name":"Sunderland","club":{"name":"Sunderland","shortName":"Sunderland","abbr":"SUN","id":29},"teamType":"FIRST","shortName":"Sunderland","id":29,"altIds":{"opta":"t56"}},"score":0}],"replay":false,"ground":{"name":"Boleyn Ground","city":"London","source":"OPTA","id":22},"neutralGround":false,"status":"C","phase":"F","outcome":"H","attendance":35033,"clock":{"secs":5400,"label":"90\u002700"},"id":4353,"altIds":{"opta":"g17684"}},{"gameweek":{"id":428,"gameweek":32},"kickoff":{"completeness":3,"millis":1049551200000,"label":"Sat 5 Apr 2003, 15:00 BST","gmtOffset":1.0},"provisionalKickoff":{"completeness":0},"teams":[{"team":{"name":"Southampton","club":{"name":"Southampton","shortName":"Southampton","abbr":"SOU","id":20},"teamType":"FIRST","shortName":"Southampton","id":20,"altIds":{"opta":"t20"}},"score":1},{"team":{"name":"West Ham United","club":{"name":"West Ham United","shortName":"West Ham","abbr":"WHU","id":25},"teamType":"FIRST","shortName":"West Ham","id":25,"altIds":{"opta":"t21"}},"score":1}],"replay":false,"ground":{"name":"St. Mary\u0027s Stadium","city":"Southampton","source":"OPTA","id":25},"neutralGround":false,"status":"C","phase":"F","outcome":"D","attendance":31941,"clock":{"secs":5400,"label":"90\u002700"},"id":4362,"altIds":{"opta":"g17656"}},{"gameweek":{"id":429,"gameweek":33},"kickoff":{"completeness":3,"millis":1050156000000,"label":"Sat 12 Apr 2003, 15:00 BST","gmtOffset":1.0},"provisionalKickoff":{"completeness":0},"teams":[{"team":{"name":"West Ham United","club":{"name":"West Ham United","shortName":"West Ham","abbr":"WHU","id":25},"teamType":"FIRST","shortName":"West Ham","id":25,"altIds":{"opta":"t21"}},"score":2},{"team":{"name":"Aston Villa","club":{"name":"Aston Villa","shortName":"Aston Villa","abbr":"AVL","id":2},"teamType":"FIRST","shortName":"Aston Villa","id":2,"altIds":{"opta":"t7"}},"score":2}],"replay":false,"ground":{"name":"Boleyn Ground","city":"London","source":"OPTA","id":22},"neutralGround":false,"status":"C","phase":"F","outcome":"D","attendance":35029,"clock":{"secs":5400,"label":"90\u002700"},"id":4375,"altIds":{"opta":"g14152"}},{"gameweek":{"id":430,"gameweek":34},"kickoff":{"completeness":3,"millis":1050760800000,"label":"Sat 19 Apr 2003, 15:00 BST","gmtOffset":1.0},"provisionalKickoff":{"completeness":0},"teams":[{"team":{"name":"Bolton Wanderers","club":{"name":"Bolton Wanderers","shortName":"Bolton","abbr":"BOL","id":27},"teamType":"FIRST","shortName":"Bolton","id":27,"altIds":{"opta":"t30"}},"score":1},{"team":{"name":"West Ham United","club":{"name":"West Ham United","shortName":"West Ham","abbr":"WHU","id":25},"teamType":"FIRST","shortName":"West Ham","id":25,"altIds":{"opta":"t21"}},"score":0}],"replay":false,"ground":{"name":"Macron Stadium","city":"Bolton","source":"OPTA","id":62},"neutralGround":false,"status":"C","phase":"F","outcome":"H","attendance":27160,"clock":{"secs":5400,"label":"90\u002700"},"id":4379,"altIds":{"opta":"g14662"}}],"ground":{"name":"Boleyn Ground","city":"London","capacity":35016,"location":{"latitude":51.5317,"longitude":0.038316},"source":"OPTA","id":22}},{"team":{"name":"West Bromwich Albion","club":{"name":"West Bromwich Albion","shortName":"West Brom","abbr":"WBA","id":36},"teamType":"FIRST","shortName":"West Brom","id":36,"altIds":{"opta":"t35"}},"position":19,"startingPosition":19,"overall":{"played":34,"won":6,"drawn":6,"lost":22,"goalsFor":24,"goalsAgainst":53,"goalsDifference":-29,"points":24},"home":{"played":16,"won":3,"drawn":4,"lost":9,"goalsFor":13,"goalsAgainst":23,"goalsDifference":-10,"points":13,"position":19},"away":{"played":18,"won":3,"drawn":2,"lost":13,"goalsFor":11,"goalsAgainst":30,"goalsDifference":-19,"points":11,"position":17},"annotations":[{"type":"R","destination":"EN_D1"}],"form":[{"gameweek":{"id":426,"gameweek":30},"kickoff":{"completeness":3,"millis":1047830700000,"label":"Sun 16 Mar 2003, 16:05 GMT"},"provisionalKickoff":{"completeness":0},"teams":[{"team":{"name":"West Bromwich Albion","club":{"name":"West Bromwich Albion","shortName":"West Brom","abbr":"WBA","id":36},"teamType":"FIRST","shortName":"West Brom","id":36,"altIds":{"opta":"t35"}},"score":0},{"team":{"name":"Chelsea","club":{"name":"Chelsea","shortName":"Chelsea","abbr":"CHE","id":4},"teamType":"FIRST","shortName":"Chelsea","id":4,"altIds":{"opta":"t8"}},"score":2}],"replay":false,"ground":{"name":"The Hawthorns","city":"West Bromwich","source":"OPTA","id":12},"neutralGround":false,"status":"C","phase":"F","outcome":"A","attendance":27024,"clock":{"secs":5400,"label":"90\u002700"},"id":4346,"altIds":{"opta":"g15194"}},{"gameweek":{"id":427,"gameweek":31},"kickoff":{"completeness":3,"millis":1048334400000,"label":"Sat 22 Mar 2003, 12:00 GMT"},"provisionalKickoff":{"completeness":0},"teams":[{"team":{"name":"Birmingham City","club":{"name":"Birmingham City","shortName":"Birmingham","abbr":"BIR","id":35},"teamType":"FIRST","shortName":"Birmingham","id":35,"altIds":{"opta":"t41"}},"score":1},{"team":{"name":"West Bromwich Albion","club":{"name":"West Bromwich Albion","shortName":"West Brom","abbr":"WBA","id":36},"teamType":"FIRST","shortName":"West Brom","id":36,"altIds":{"opta":"t35"}},"score":0}],"replay":false,"ground":{"name":"St. Andrew\u0027s Stadium","city":"Birmingham","source":"OPTA","id":67},"neutralGround":false,"status":"C","phase":"F","outcome":"H","attendance":29449,"clock":{"secs":5400,"label":"90\u002700"},"id":4347,"altIds":{"opta":"g14218"}},{"gameweek":{"id":428,"gameweek":32},"kickoff":{"completeness":3,"millis":1049551200000,"label":"Sat 5 Apr 2003, 15:00 BST","gmtOffset":1.0},"provisionalKickoff":{"completeness":0},"teams":[{"team":{"name":"Middlesbrough","club":{"name":"Middlesbrough","shortName":"Middlesbrough","abbr":"MID","id":13},"teamType":"FIRST","shortName":"Middlesbrough","id":13,"altIds":{"opta":"t25"}},"score":3},{"team":{"name":"West Bromwich Albion","club":{"name":"West Bromwich Albion","shortName":"West Brom","abbr":"WBA","id":36},"teamType":"FIRST","shortName":"West Brom","id":36,"altIds":{"opta":"t35"}},"score":0}],"replay":false,"ground":{"name":"Riverside Stadium","city":"Middlesbrough","source":"OPTA","id":61},"neutralGround":false,"status":"C","phase":"F","outcome":"H","attendance":30187,"clock":{"secs":5400,"label":"90\u002700"},"id":4361,"altIds":{"opta":"g17184"}},{"gameweek":{"id":429,"gameweek":33},"kickoff":{"completeness":3,"millis":1050156000000,"label":"Sat 12 Apr 2003, 15:00 BST","gmtOffset":1.0},"provisionalKickoff":{"completeness":0},"teams":[{"team":{"name":"West Bromwich Albion","club":{"name":"West Bromwich Albion","shortName":"West Brom","abbr":"WBA","id":36},"teamType":"FIRST","shortName":"West Brom","id":36,"altIds":{"opta":"t35"}},"score":1},{"team":{"name":"Everton","club":{"name":"Everton","shortName":"Everton","abbr":"EVE","id":7},"teamType":"FIRST","shortName":"Everton","id":7,"altIds":{"opta":"t11"}},"score":2}],"replay":false,"ground":{"name":"The Hawthorns","city":"West Bromwich","source":"OPTA","id":12},"neutralGround":false,"status":"C","phase":"F","outcome":"A","attendance":27039,"clock":{"secs":5400,"label":"90\u002700"},"id":4374,"altIds":{"opta":"g15999"}},{"gameweek":{"id":430,"gameweek":34},"kickoff":{"completeness":3,"millis":1050760800000,"label":"Sat 19 Apr 2003, 15:00 BST","gmtOffset":1.0},"provisionalKickoff":{"completeness":0},"teams":[{"team":{"name":"Sunderland","club":{"name":"Sunderland","shortName":"Sunderland","abbr":"SUN","id":29},"teamType":"FIRST","shortName":"Sunderland","id":29,"altIds":{"opta":"t56"}},"score":1},{"team":{"name":"West Bromwich Albion","club":{"name":"West Bromwich Albion","shortName":"West Brom","abbr":"WBA","id":36},"teamType":"FIRST","shortName":"West Brom","id":36,"altIds":{"opta":"t35"}},"score":2}],"replay":false,"ground":{"name":"Stadium of Light","city":"Sunderland","source":"OPTA","id":17},"neutralGround":false,"status":"C","phase":"F","outcome":"A","attendance":36025,"clock":{"secs":5400,"label":"90\u002700"},"id":4386,"altIds":{"opta":"g17685"}}],"ground":{"name":"The Hawthorns","city":"West Bromwich","capacity":26272,"location":{"latitude":52.5099,"longitude":-1.9638},"source":"OPTA","id":12}},{"team":{"name":"Sunderland","club":{"name":"Sunderland","shortName":"Sunderland","abbr":"SUN","id":29},"teamType":"FIRST","shortName":"Sunderland","id":29,"altIds":{"opta":"t56"}},"position":20,"startingPosition":20,"overall":{"played":34,"won":4,"drawn":7,"lost":23,"goalsFor":21,"goalsAgainst":56,"goalsDifference":-35,"points":19},"home":{"played":17,"won":3,"drawn":2,"lost":12,"goalsFor":11,"goalsAgainst":26,"goalsDifference":-15,"points":11,"position":20},"away":{"played":17,"won":1,"drawn":5,"lost":11,"goalsFor":10,"goalsAgainst":30,"goalsDifference":-20,"points":8,"position":20},"annotations":[{"type":"R","destination":"EN_D1"}],"form":[{"gameweek":{"id":426,"gameweek":30},"kickoff":{"completeness":3,"millis":1047740400000,"label":"Sat 15 Mar 2003, 15:00 GMT"},"provisionalKickoff":{"completeness":0},"teams":[{"team":{"name":"Sunderland","club":{"name":"Sunderland","shortName":"Sunderland","abbr":"SUN","id":29},"teamType":"FIRST","shortName":"Sunderland","id":29,"altIds":{"opta":"t56"}},"score":0},{"team":{"name":"Bolton Wanderers","club":{"name":"Bolton Wanderers","shortName":"Bolton","abbr":"BOL","id":27},"teamType":"FIRST","shortName":"Bolton","id":27,"altIds":{"opta":"t30"}},"score":2}],"replay":false,"ground":{"name":"Stadium of Light","city":"Sunderland","source":"OPTA","id":17},"neutralGround":false,"status":"C","phase":"F","outcome":"A","attendance":42124,"clock":{"secs":5400,"label":"90\u002700"},"id":4343,"altIds":{"opta":"g14658"}},{"gameweek":{"id":427,"gameweek":31},"kickoff":{"completeness":3,"millis":1048345200000,"label":"Sat 22 Mar 2003, 15:00 GMT"},"provisionalKickoff":{"completeness":0},"teams":[{"team":{"name":"West Ham United","club":{"name":"West Ham United","shortName":"West Ham","abbr":"WHU","id":25},"teamType":"FIRST","shortName":"West Ham","id":25,"altIds":{"opta":"t21"}},"score":2},{"team":{"name":"Sunderland","club":{"name":"Sunderland","shortName":"Sunderland","abbr":"SUN","id":29},"teamType":"FIRST","shortName":"Sunderland","id":29,"altIds":{"opta":"t56"}},"score":0}],"replay":false,"ground":{"name":"Boleyn Ground","city":"London","source":"OPTA","id":22},"neutralGround":false,"status":"C","phase":"F","outcome":"H","attendance":35033,"clock":{"secs":5400,"label":"90\u002700"},"id":4353,"altIds":{"opta":"g17684"}},{"gameweek":{"id":428,"gameweek":32},"kickoff":{"completeness":3,"millis":1049551200000,"label":"Sat 5 Apr 2003, 15:00 BST","gmtOffset":1.0},"provisionalKickoff":{"completeness":0},"teams":[{"team":{"name":"Sunderland","club":{"name":"Sunderland","shortName":"Sunderland","abbr":"SUN","id":29},"teamType":"FIRST","shortName":"Sunderland","id":29,"altIds":{"opta":"t56"}},"score":1},{"team":{"name":"Chelsea","club":{"name":"Chelsea","shortName":"Chelsea","abbr":"CHE","id":4},"teamType":"FIRST","shortName":"Chelsea","id":4,"altIds":{"opta":"t8"}},"score":2}],"replay":false,"ground":{"name":"Stadium of Light","city":"Sunderland","source":"OPTA","id":17},"neutralGround":false,"status":"C","phase":"F","outcome":"A","attendance":40011,"clock":{"secs":5400,"label":"90\u002700"},"id":4363,"altIds":{"opta":"g15196"}},{"gameweek":{"id":429,"gameweek":33},"kickoff":{"completeness":3,"millis":1050156000000,"label":"Sat 12 Apr 2003, 15:00 BST","gmtOffset":1.0},"provisionalKickoff":{"completeness":0},"teams":[{"team":{"name":"Birmingham City","club":{"name":"Birmingham City","shortName":"Birmingham","abbr":"BIR","id":35},"teamType":"FIRST","shortName":"Birmingham","id":35,"altIds":{"opta":"t41"}},"score":2},{"team":{"name":"Sunderland","club":{"name":"Sunderland","shortName":"Sunderland","abbr":"SUN","id":29},"teamType":"FIRST","shortName":"Sunderland","id":29,"altIds":{"opta":"t56"}},"score":0}],"replay":false,"ground":{"name":"St. Andrew\u0027s Stadium","city":"Birmingham","source":"OPTA","id":67},"neutralGround":false,"status":"C","phase":"F","outcome":"H","attendance":29132,"clock":{"secs":5400,"label":"90\u002700"},"id":4367,"altIds":{"opta":"g14220"}},{"gameweek":{"id":430,"gameweek":34},"kickoff":{"completeness":3,"millis":1050760800000,"label":"Sat 19 Apr 2003, 15:00 BST","gmtOffset":1.0},"provisionalKickoff":{"completeness":0},"teams":[{"team":{"name":"Sunderland","club":{"name":"Sunderland","shortName":"Sunderland","abbr":"SUN","id":29},"teamType":"FIRST","shortName":"Sunderland","id":29,"altIds":{"opta":"t56"}},"score":1},{"team":{"name":"West Bromwich Albion","club":{"name":"West Bromwich Albion","shortName":"West Brom","abbr":"WBA","id":36},"teamType":"FIRST","shortName":"West Brom","id":36,"altIds":{"opta":"t35"}},"score":2}],"replay":false,"ground":{"name":"Stadium of Light","city":"Sunderland","source":"OPTA","id":17},"neutralGround":false,"status":"C","phase":"F","outcome":"A","attendance":36025,"clock":{"secs":5400,"label":"90\u002700"},"id":4386,"altIds":{"opta":"g17685"}}],"ground":{"name":"Stadium of Light","city":"Sunderland","capacity":49000,"location":{"latitude":54.9141,"longitude":-1.3893},"source":"OPTA","id":17}}]}]}